[{"id":1,"first_name":"Nonah","last_name":"Stannah","email":"nstannah0@123-reg.co.uk"},
{"id":2,"first_name":"Darbee","last_name":"Anthoney","email":"danthoney1@bloglines.com"},
{"id":3,"first_name":"Carlene","last_name":"Landell","email":"clandell2@forbes.com"},
{"id":4,"first_name":"Cosmo","last_name":"Arnald","email":"carnald3@vistaprint.com"},
{"id":5,"first_name":"Farlay","last_name":"Munkley","email":"fmunkley4@slate.com"},
{"id":6,"first_name":"Flint","last_name":"Eneas","email":"feneas5@amazon.de"},
{"id":7,"first_name":"Viviana","last_name":"Thomann","email":"vthomann6@ycombinator.com"},
{"id":8,"first_name":"Sim","last_name":"Reoch","email":"sreoch7@spiegel.de"},
{"id":9,"first_name":"Herby","last_name":"Sore","email":"hsore8@goo.gl"},
{"id":10,"first_name":"Brady","last_name":"Towson","email":"btowson9@comcast.net"},
{"id":11,"first_name":"Doretta","last_name":"Juschke","email":"djuschkea@liveinternet.ru"},
{"id":12,"first_name":"Miof mela","last_name":"Gerriets","email":"mgerrietsb@usda.gov"},
{"id":13,"first_name":"Tiebold","last_name":"Mardoll","email":"tmardollc@statcounter.com"},
{"id":14,"first_name":"Tuckie","last_name":"Capner","email":"tcapnerd@disqus.com"},
{"id":15,"first_name":"Timotheus","last_name":"MacCorkell","email":"tmaccorkelle@g.co"},
{"id":16,"first_name":"Dell","last_name":"Seward","email":"dsewardf@cafepress.com"},
{"id":17,"first_name":"Correy","last_name":"Piccop","email":"cpiccopg@liveinternet.ru"},
{"id":18,"first_name":"Korrie","last_name":"Rewan","email":"krewanh@ocn.ne.jp"},
{"id":19,"first_name":"Sissie","last_name":"Petersen","email":"speterseni@mtv.com"},
{"id":20,"first_name":"Bevin","last_name":"Godson","email":"bgodsonj@independent.co.uk"},
{"id":21,"first_name":"Mahala","last_name":"Bruniges","email":"mbrunigesk@reference.com"},
{"id":22,"first_name":"Terence","last_name":"Chambers","email":"tchambersl@indiatimes.com"},
{"id":23,"first_name":"Rudolph","last_name":"Klehyn","email":"rklehynm@dell.com"},
{"id":24,"first_name":"Mellie","last_name":"Fritchley","email":"mfritchleyn@vinaora.com"},
{"id":25,"first_name":"Agustin","last_name":"Bindon","email":"abindono@mlb.com"},
{"id":26,"first_name":"Nataniel","last_name":"Serfati","email":"nserfatip@printfriendly.com"},
{"id":27,"first_name":"Ossie","last_name":"Jubb","email":"ojubbq@naver.com"},
{"id":28,"first_name":"Logan","last_name":"Cheak","email":"lcheakr@bandcamp.com"},
{"id":29,"first_name":"Stacia","last_name":"Moffat","email":"smoffats@goo.ne.jp"},
{"id":30,"first_name":"Allene","last_name":"O' Mulderrig","email":"aomulderrigt@meetup.com"},
{"id":31,"first_name":"Carey","last_name":"Patillo","email":"cpatillou@tinyurl.com"},
{"id":32,"first_name":"Rodolphe","last_name":"Perllman","email":"rperllmanv@booking.com"},
{"id":33,"first_name":"Temple","last_name":"Mackriell","email":"tmackriellw@edublogs.org"},
{"id":34,"first_name":"Harmony","last_name":"Brugger","email":"hbruggerx@vkontakte.ru"},
{"id":35,"first_name":"Kettie","last_name":"Blyth","email":"kblythy@baidu.com"},
{"id":36,"first_name":"Eliza","last_name":"Yashunin","email":"eyashuninz@linkedin.com"},
{"id":37,"first_name":"Bettina","last_name":"Enriquez","email":"benriquez10@nifty.com"},
{"id":38,"first_name":"Cory","last_name":"Watson-Brown","email":"cwatsonbrown11@sciencedaily.com"},
{"id":39,"first_name":"Pieter","last_name":"Falkinder","email":"pfalkinder12@gmpg.org"},
{"id":40,"first_name":"Ethelda","last_name":"Paradise","email":"eparadise13@eepurl.com"},
{"id":41,"first_name":"Poppy","last_name":"Hehnke","email":"phehnke14@accuweather.com"},
{"id":42,"first_name":"Nedda","last_name":"Quantrill","email":"nquantrill15@naver.com"},
{"id":43,"first_name":"Abigail","last_name":"Fawson","email":"afawson16@wikimedia.org"},
{"id":44,"first_name":"Ulla","last_name":"Thuillier","email":"uthuillier17@who.int"},
{"id":45,"first_name":"Ginny","last_name":"Jailler","email":"gjailler18@microsoft.com"},
{"id":46,"first_name":"Sibylle","last_name":"MacArte","email":"smacarte19@marriott.com"},
{"id":47,"first_name":"Clareta","last_name":"Aldwich","email":"caldwich1a@army.mil"},
{"id":48,"first_name":"Sarina","last_name":"Dunkinson","email":"sdunkinson1b@hubpages.com"},
{"id":49,"first_name":"Evelyn","last_name":"Fortye","email":"efortye1c@amazon.co.jp"},
{"id":50,"first_name":"Dana","last_name":"Wheldon","email":"dwheldon1d@mashable.com"},
{"id":51,"first_name":"Dirk","last_name":"Lamacraft","email":"dlamacraft1e@earthlink.net"},
{"id":52,"first_name":"Frederic","last_name":"Grinishin","email":"fgrinishin1f@salon.com"},
{"id":53,"first_name":"Ninnette","last_name":"Hancill","email":"nhancill1g@columbia.edu"},
{"id":54,"first_name":"Peggy","last_name":"Wisham","email":"pwisham1h@ycombinator.com"},
{"id":55,"first_name":"Daryl","last_name":"Cicerone","email":"dcicerone1i@hugedomains.com"},
{"id":56,"first_name":"Stephanie","last_name":"Studdeard","email":"sstuddeard1j@bloglovin.com"},
{"id":57,"first_name":"Alina","last_name":"Cornier","email":"acornier1k@hp.com"},
{"id":58,"first_name":"Elsinore","last_name":"Dreakin","email":"edreakin1l@bloglovin.com"},
{"id":59,"first_name":"Krisha","last_name":"Devo","email":"kdevo1m@youtube.com"},
{"id":60,"first_name":"Rivy","last_name":"Burds","email":"rburds1n@shutterfly.com"},
{"id":61,"first_name":"Yorgo","last_name":"Kezourec","email":"ykezourec1o@who.int"},
{"id":62,"first_name":"Benoite","last_name":"Howell","email":"bhowell1p@howstuffworks.com"},
{"id":63,"first_name":"Brande","last_name":"Wrinch","email":"bwrinch1q@wiley.com"},
{"id":64,"first_name":"Karrie","last_name":"Duding","email":"kduding1r@ca.gov"},
{"id":65,"first_name":"Lynn","last_name":"Bladesmith","email":"lbladesmith1s@ft.com"},
{"id":66,"first_name":"Monro","last_name":"Stannus","email":"mstannus1t@ycombinator.com"},
{"id":67,"first_name":"Barnebas","last_name":"Dubique","email":"bdubique1u@hubpages.com"},
{"id":68,"first_name":"Ermengarde","last_name":"Alltimes","email":"ealltimes1v@redcross.org"},
{"id":69,"first_name":"Brinna","last_name":"Peacocke","email":"bpeacocke1w@mozilla.org"},
{"id":70,"first_name":"Cordey","last_name":"Crommett","email":"ccrommett1x@cpanel.net"},
{"id":71,"first_name":"Diana","last_name":"O'Concannon","email":"doconcannon1y@businessweek.com"},
{"id":72,"first_name":"Emmalyn","last_name":"Solley","email":"esolley1z@livejournal.com"},
{"id":73,"first_name":"Gonzalo","last_name":"Freeman","email":"gfreeman20@discuz.net"},
{"id":74,"first_name":"Dexter","last_name":"Cowhig","email":"dcowhig21@twitter.com"},
{"id":75,"first_name":"Rudolph","last_name":"Jiran","email":"rjiran22@wiley.com"},
{"id":76,"first_name":"Dewie","last_name":"Trout","email":"dtrout23@sun.com"},
{"id":77,"first_name":"Boycey","last_name":"Fulbrook","email":"bfulbrook24@google.com.hk"},
{"id":78,"first_name":"Alonso","last_name":"Veck","email":"aveck25@google.pl"},
{"id":79,"first_name":"Darlene","last_name":"Dyer","email":"ddyer26@altervista.org"},
{"id":80,"first_name":"Genevieve","last_name":"Tombs","email":"gtombs27@fc2.com"},
{"id":81,"first_name":"Gerrie","last_name":"Pestricke","email":"gpestricke28@yellowbook.com"},
{"id":82,"first_name":"Charlean","last_name":"Lehenmann","email":"clehenmann29@icio.us"},
{"id":83,"first_name":"Krista","last_name":"Rawlins","email":"krawlins2a@shop-pro.jp"},
{"id":84,"first_name":"Dewain","last_name":"Thomsen","email":"dthomsen2b@wunderground.com"},
{"id":85,"first_name":"Trever","last_name":"Maskrey","email":"tmaskrey2c@harvard.edu"},
{"id":86,"first_name":"Agnese","last_name":"Phippin","email":"aphippin2d@mlb.com"},
{"id":87,"first_name":"Ritchie","last_name":"Bucky","email":"rbucky2e@jugem.jp"},
{"id":88,"first_name":"Engelbert","last_name":"Scapelhorn","email":"escapelhorn2f@trellian.com"},
{"id":89,"first_name":"Tessy","last_name":"Roels","email":"troels2g@tinypic.com"},
{"id":90,"first_name":"Jacques","last_name":"Eastop","email":"jeastop2h@webs.com"},
{"id":91,"first_name":"Jarvis","last_name":"Quickenden","email":"jquickenden2i@meetup.com"},
{"id":92,"first_name":"Sunny","last_name":"Spadeck","email":"sspadeck2j@sfgate.com"},
{"id":93,"first_name":"Ulrich","last_name":"Treske","email":"utreske2k@behance.net"},
{"id":94,"first_name":"Olivette","last_name":"Perrycost","email":"operrycost2l@ehow.com"},
{"id":95,"first_name":"Georgia","last_name":"Bartalot","email":"gbartalot2m@free.fr"},
{"id":96,"first_name":"Wilona","last_name":"Morfield","email":"wmorfield2n@miibeian.gov.cn"},
{"id":97,"first_name":"Carol","last_name":"Chevis","email":"cchevis2o@icio.us"},
{"id":98,"first_name":"Obediah","last_name":"Lewtey","email":"olewtey2p@ehow.com"},
{"id":99,"first_name":"Renato","last_name":"Berrane","email":"rberrane2q@nationalgeographic.com"},
{"id":100,"first_name":"Emmy","last_name":"Aldersey","email":"ealdersey2r@redcross.org"},
{"id":101,"first_name":"Sher","last_name":"Suddell","email":"ssuddell2s@who.int"},
{"id":102,"first_name":"Trenton","last_name":"Verrechia","email":"tverrechia2t@comsenz.com"},
{"id":103,"first_name":"Reinold","last_name":"Flory","email":"rflory2u@yolasite.com"},
{"id":104,"first_name":"Carlynn","last_name":"Leggon","email":"cleggon2v@dyndns.org"},
{"id":105,"first_name":"Ninnette","last_name":"Fidele","email":"nfidele2w@samsung.com"},
{"id":106,"first_name":"Markus","last_name":"Verrier","email":"mverrier2x@cornell.edu"},
{"id":107,"first_name":"Ron","last_name":"Keld","email":"rkeld2y@blogtalkradio.com"},
{"id":108,"first_name":"Innis","last_name":"Bolino","email":"ibolino2z@reference.com"},
{"id":109,"first_name":"Traci","last_name":"Yurlov","email":"tyurlov30@creativecommons.org"},
{"id":110,"first_name":"Shadow","last_name":"Bellamy","email":"sbellamy31@bigcartel.com"},
{"id":111,"first_name":"Xever","last_name":"Mendoza","email":"xmendoza32@surveymonkey.com"},
{"id":112,"first_name":"Barry","last_name":"Ionnisian","email":"bionnisian33@rambler.ru"},
{"id":113,"first_name":"Elsie","last_name":"Slowan","email":"eslowan34@pagesperso-orange.fr"},
{"id":114,"first_name":"Milena","last_name":"Woodburne","email":"mwoodburne35@china.com.cn"},
{"id":115,"first_name":"Derwin","last_name":"Penna","email":"dpenna36@yolasite.com"},
{"id":116,"first_name":"Kelvin","last_name":"Saunders","email":"ksaunders37@facebook.com"},
{"id":117,"first_name":"Yank","last_name":"Prys","email":"yprys38@privacy.gov.au"},
{"id":118,"first_name":"Rebe","last_name":"Schmidt","email":"rschmidt39@feedburner.com"},
{"id":119,"first_name":"Mandie","last_name":"Kluss","email":"mkluss3a@pinterest.com"},
{"id":120,"first_name":"Jedediah","last_name":"Mechem","email":"jmechem3b@g.co"},
{"id":121,"first_name":"Ravid","last_name":"Chatel","email":"rchatel3c@chicagotribune.com"},
{"id":122,"first_name":"Piggy","last_name":"Werrilow","email":"pwerrilow3d@forbes.com"},
{"id":123,"first_name":"Ellery","last_name":"Daventry","email":"edaventry3e@nasa.gov"},
{"id":124,"first_name":"Lavinie","last_name":"Patmore","email":"lpatmore3f@hubpages.com"},
{"id":125,"first_name":"Aurore","last_name":"Songhurst","email":"asonghurst3g@t-online.de"},
{"id":126,"first_name":"Jaye","last_name":"Trousdell","email":"jtrousdell3h@so-net.ne.jp"},
{"id":127,"first_name":"Eldredge","last_name":"Arnault","email":"earnault3i@go.com"},
{"id":128,"first_name":"Dorrie","last_name":"Dace","email":"ddace3j@umich.edu"},
{"id":129,"first_name":"Vikki","last_name":"Rohlf","email":"vrohlf3k@cbc.ca"},
{"id":130,"first_name":"Bernita","last_name":"Fonso","email":"bfonso3l@biblegateway.com"},
{"id":131,"first_name":"Scarlet","last_name":"Sams","email":"ssams3m@omniture.com"},
{"id":132,"first_name":"Naomi","last_name":"Fuster","email":"nfuster3n@slideshare.net"},
{"id":133,"first_name":"Shayne","last_name":"Faithorn","email":"sfaithorn3o@histats.com"},
{"id":134,"first_name":"Dallas","last_name":"Kliemchen","email":"dkliemchen3p@pen.io"},
{"id":135,"first_name":"Felisha","last_name":"Greenaway","email":"fgreenaway3q@com.com"},
{"id":136,"first_name":"Ivan","last_name":"Olpin","email":"iolpin3r@istockphoto.com"},
{"id":137,"first_name":"Renault","last_name":"Terney","email":"rterney3s@php.net"},
{"id":138,"first_name":"Erda","last_name":"Feehily","email":"efeehily3t@instagram.com"},
{"id":139,"first_name":"Townie","last_name":"McSweeney","email":"tmcsweeney3u@irs.gov"},
{"id":140,"first_name":"Salli","last_name":"Coomber","email":"scoomber3v@theglobeandmail.com"},
{"id":141,"first_name":"Hyatt","last_name":"Liddard","email":"hliddard3w@cam.ac.uk"},
{"id":142,"first_name":"Kakalina","last_name":"Fawlks","email":"kfawlks3x@storify.com"},
{"id":143,"first_name":"Mirabella","last_name":"Prahl","email":"mprahl3y@mtv.com"},
{"id":144,"first_name":"Bengt","last_name":"Notti","email":"bnotti3z@ameblo.jp"},
{"id":145,"first_name":"Basile","last_name":"Croote","email":"bcroote40@myspace.com"},
{"id":146,"first_name":"Bran","last_name":"Veschambes","email":"bveschambes41@slideshare.net"},
{"id":147,"first_name":"Ariella","last_name":"Stollsteiner","email":"astollsteiner42@wordpress.org"},
{"id":148,"first_name":"Abramo","last_name":"Cadman","email":"acadman43@google.nl"},
{"id":149,"first_name":"Frannie","last_name":"Rambadt","email":"frambadt44@accuweather.com"},
{"id":150,"first_name":"Sonya","last_name":"Reffe","email":"sreffe45@mtv.com"},
{"id":151,"first_name":"Link","last_name":"Chippindall","email":"lchippindall46@issuu.com"},
{"id":152,"first_name":"Merwin","last_name":"Dowyer","email":"mdowyer47@arstechnica.com"},
{"id":153,"first_name":"Lind","last_name":"Seabert","email":"lseabert48@geocities.jp"},
{"id":154,"first_name":"Haslett","last_name":"Leet","email":"hleet49@prnewswire.com"},
{"id":155,"first_name":"Maxy","last_name":"Yude","email":"myude4a@cornell.edu"},
{"id":156,"first_name":"Harley","last_name":"Kempshall","email":"hkempshall4b@cloudflare.com"},
{"id":157,"first_name":"Margie","last_name":"Eck","email":"meck4c@time.com"},
{"id":158,"first_name":"Tresa","last_name":"Jude","email":"tjude4d@mtv.com"},
{"id":159,"first_name":"Dedra","last_name":"Beckhurst","email":"dbeckhurst4e@fotki.com"},
{"id":160,"first_name":"Kelby","last_name":"Berriball","email":"kberriball4f@seesaa.net"},
{"id":161,"first_name":"Anne","last_name":"Branni","email":"abranni4g@blogs.com"},
{"id":162,"first_name":"Marchelle","last_name":"Ambrosio","email":"mambrosio4h@gov.uk"},
{"id":163,"first_name":"Albrecht","last_name":"Woonton","email":"awoonton4i@elpais.com"},
{"id":164,"first_name":"Jamie","last_name":"Castanone","email":"jcastanone4j@goo.ne.jp"},
{"id":165,"first_name":"Abbi","last_name":"Manntschke","email":"amanntschke4k@census.gov"},
{"id":166,"first_name":"Keith","last_name":"Brazil","email":"kbrazil4l@flickr.com"},
{"id":167,"first_name":"Car","last_name":"Swettenham","email":"cswettenham4m@over-blog.com"},
{"id":168,"first_name":"Jessalin","last_name":"Lindenstrauss","email":"jlindenstrauss4n@soup.io"},
{"id":169,"first_name":"Umeko","last_name":"Dales","email":"udales4o@zimbio.com"},
{"id":170,"first_name":"Nathanial","last_name":"Gamil","email":"ngamil4p@sohu.com"},
{"id":171,"first_name":"Kennedy","last_name":"Godsal","email":"kgodsal4q@exblog.jp"},
{"id":172,"first_name":"Gasper","last_name":"Rymer","email":"grymer4r@canalblog.com"},
{"id":173,"first_name":"Marcie","last_name":"Concannon","email":"mconcannon4s@shutterfly.com"},
{"id":174,"first_name":"Kali","last_name":"Sibbering","email":"ksibbering4t@ifeng.com"},
{"id":175,"first_name":"Pooh","last_name":"Baskett","email":"pbaskett4u@mapquest.com"},
{"id":176,"first_name":"Mozes","last_name":"Wormleighton","email":"mwormleighton4v@indiegogo.com"},
{"id":177,"first_name":"Elga","last_name":"Goodyer","email":"egoodyer4w@engadget.com"},
{"id":178,"first_name":"Kaye","last_name":"Janks","email":"kjanks4x@mysql.com"},
{"id":179,"first_name":"Willis","last_name":"Clemon","email":"wclemon4y@indiatimes.com"},
{"id":180,"first_name":"Trev","last_name":"Birrell","email":"tbirrell4z@aboutads.info"},
{"id":181,"first_name":"Gisele","last_name":"Gerriets","email":"ggerriets50@spiegel.de"},
{"id":182,"first_name":"Nicolas","last_name":"Stoeck","email":"nstoeck51@barnesandnoble.com"},
{"id":183,"first_name":"Lavinia","last_name":"Titford","email":"ltitford52@github.com"},
{"id":184,"first_name":"Dee","last_name":"Churchley","email":"dchurchley53@bluehost.com"},
{"id":185,"first_name":"Lari","last_name":"Dickins","email":"ldickins54@prlog.org"},
{"id":186,"first_name":"Hillary","last_name":"Sambedge","email":"hsambedge55@gravatar.com"},
{"id":187,"first_name":"Justin","last_name":"Yakunikov","email":"jyakunikov56@trellian.com"},
{"id":188,"first_name":"Caldwell","last_name":"Annetts","email":"cannetts57@columbia.edu"},
{"id":189,"first_name":"Reynold","last_name":"Craigmile","email":"rcraigmile58@booking.com"},
{"id":190,"first_name":"Thedric","last_name":"Worsalls","email":"tworsalls59@blog.com"},
{"id":191,"first_name":"Angelica","last_name":"Niccolls","email":"aniccolls5a@yellowpages.com"},
{"id":192,"first_name":"Gayla","last_name":"Urlich","email":"gurlich5b@dion.ne.jp"},
{"id":193,"first_name":"Ajay","last_name":"Folan","email":"afolan5c@vimeo.com"},
{"id":194,"first_name":"Rois","last_name":"Joseland","email":"rjoseland5d@t.co"},
{"id":195,"first_name":"Fredra","last_name":"Mathen","email":"fmathen5e@shinystat.com"},
{"id":196,"first_name":"Maryl","last_name":"Bogey","email":"mbogey5f@harvard.edu"},
{"id":197,"first_name":"Arleyne","last_name":"Manssuer","email":"amanssuer5g@sphinn.com"},
{"id":198,"first_name":"Debra","last_name":"Dracey","email":"ddracey5h@smh.com.au"},
{"id":199,"first_name":"Krissy","last_name":"Muirhead","email":"kmuirhead5i@ft.com"},
{"id":200,"first_name":"Cherey","last_name":"Rawe","email":"crawe5j@adobe.com"},
{"id":201,"first_name":"Annabelle","last_name":"Noar","email":"anoar5k@domainmarket.com"},
{"id":202,"first_name":"Raquel","last_name":"Marvelley","email":"rmarvelley5l@discovery.com"},
{"id":203,"first_name":"Brose","last_name":"Berisford","email":"bberisford5m@nyu.edu"},
{"id":204,"first_name":"Noak","last_name":"Creeghan","email":"ncreeghan5n@google.co.uk"},
{"id":205,"first_name":"Benny","last_name":"Hillatt","email":"bhillatt5o@amazon.de"},
{"id":206,"first_name":"Ignacius","last_name":"Bastie","email":"ibastie5p@opera.com"},
{"id":207,"first_name":"Galvan","last_name":"Gunthorp","email":"ggunthorp5q@deviantart.com"},
{"id":208,"first_name":"Lenna","last_name":"Scrinage","email":"lscrinage5r@thetimes.co.uk"},
{"id":209,"first_name":"Rosaleen","last_name":"Baitman","email":"rbaitman5s@webmd.com"},
{"id":210,"first_name":"Burnaby","last_name":"Barnshaw","email":"bbarnshaw5t@elegantthemes.com"},
{"id":211,"first_name":"Coleen","last_name":"Michelotti","email":"cmichelotti5u@privacy.gov.au"},
{"id":212,"first_name":"Josy","last_name":"Bezzant","email":"jbezzant5v@fc2.com"},
{"id":213,"first_name":"Filide","last_name":"Yon","email":"fyon5w@webs.com"},
{"id":214,"first_name":"Arden","last_name":"Blincko","email":"ablincko5x@psu.edu"},
{"id":215,"first_name":"Tiff","last_name":"Panichelli","email":"tpanichelli5y@oracle.com"},
{"id":216,"first_name":"Alvie","last_name":"Guidetti","email":"aguidetti5z@java.com"},
{"id":217,"first_name":"Suzie","last_name":"Clancy","email":"sclancy60@angelfire.com"},
{"id":218,"first_name":"Walsh","last_name":"Curr","email":"wcurr61@unc.edu"},
{"id":219,"first_name":"Waldo","last_name":"Flatte","email":"wflatte62@ning.com"},
{"id":220,"first_name":"Terrell","last_name":"Kensington","email":"tkensington63@a8.net"},
{"id":221,"first_name":"Dusty","last_name":"McGlaughn","email":"dmcglaughn64@indiegogo.com"},
{"id":222,"first_name":"Jillene","last_name":"Foxton","email":"jfoxton65@statcounter.com"},
{"id":223,"first_name":"Marlee","last_name":"Bing","email":"mbing66@diigo.com"},
{"id":224,"first_name":"L;urette","last_name":"Smallthwaite","email":"lsmallthwaite67@g.co"},
{"id":225,"first_name":"Milissent","last_name":"Brower","email":"mbrower68@smh.com.au"},
{"id":226,"first_name":"Philipa","last_name":"McSporrin","email":"pmcsporrin69@studiopress.com"},
{"id":227,"first_name":"Gnni","last_name":"Lead","email":"glead6a@bluehost.com"},
{"id":228,"first_name":"Gertruda","last_name":"Turone","email":"gturone6b@slideshare.net"},
{"id":229,"first_name":"Rafi","last_name":"Partner","email":"rpartner6c@quantcast.com"},
{"id":230,"first_name":"Derick","last_name":"Louche","email":"dlouche6d@usatoday.com"},
{"id":231,"first_name":"Joellyn","last_name":"Lewinton","email":"jlewinton6e@usgs.gov"},
{"id":232,"first_name":"Bryant","last_name":"Durran","email":"bdurran6f@disqus.com"},
{"id":233,"first_name":"Shelli","last_name":"Magarrell","email":"smagarrell6g@umn.edu"},
{"id":234,"first_name":"Izzy","last_name":"Braisted","email":"ibraisted6h@livejournal.com"},
{"id":235,"first_name":"Thomasina","last_name":"Fluit","email":"tfluit6i@nbcnews.com"},
{"id":236,"first_name":"Marjy","last_name":"Peddersen","email":"mpeddersen6j@t-online.de"},
{"id":237,"first_name":"Haskell","last_name":"Foston","email":"hfoston6k@a8.net"},
{"id":238,"first_name":"Guinna","last_name":"Jarrel","email":"gjarrel6l@cornell.edu"},
{"id":239,"first_name":"Bird","last_name":"Yven","email":"byven6m@aol.com"},
{"id":240,"first_name":"Erl","last_name":"MacGillacolm","email":"emacgillacolm6n@spotify.com"},
{"id":241,"first_name":"Wally","last_name":"Corsham","email":"wcorsham6o@whitehouse.gov"},
{"id":242,"first_name":"Astrix","last_name":"Minico","email":"aminico6p@engadget.com"},
{"id":243,"first_name":"Valina","last_name":"Rau","email":"vrau6q@java.com"},
{"id":244,"first_name":"Leicester","last_name":"Matoshin","email":"lmatoshin6r@tiny.cc"},
{"id":245,"first_name":"Michelina","last_name":"Franzen","email":"mfranzen6s@is.gd"},
{"id":246,"first_name":"Issi","last_name":"Doyle","email":"idoyle6t@unblog.fr"},
{"id":247,"first_name":"Rosita","last_name":"Ditchburn","email":"rditchburn6u@ehow.com"},
{"id":248,"first_name":"Zitella","last_name":"Gethyn","email":"zgethyn6v@comcast.net"},
{"id":249,"first_name":"Leslie","last_name":"Skotcher","email":"lskotcher6w@addtoany.com"},
{"id":250,"first_name":"Nerissa","last_name":"Pithie","email":"npithie6x@printfriendly.com"},
{"id":251,"first_name":"Sari","last_name":"Idney","email":"sidney6y@blinklist.com"},
{"id":252,"first_name":"Ninette","last_name":"Beecker","email":"nbeecker6z@google.pl"},
{"id":253,"first_name":"Vilma","last_name":"Kille","email":"vkille70@telegraph.co.uk"},
{"id":254,"first_name":"Clemens","last_name":"Mayor","email":"cmayor71@ihg.com"},
{"id":255,"first_name":"Jenni","last_name":"MacCall","email":"jmaccall72@soundcloud.com"},
{"id":256,"first_name":"Myer","last_name":"Kerrigan","email":"mkerrigan73@newsvine.com"},
{"id":257,"first_name":"Alexis","last_name":"McMeyler","email":"amcmeyler74@salon.com"},
{"id":258,"first_name":"Aprilette","last_name":"Scott","email":"ascott75@t-online.de"},
{"id":259,"first_name":"Siana","last_name":"Giovannetti","email":"sgiovannetti76@soundcloud.com"},
{"id":260,"first_name":"Reeta","last_name":"Guisot","email":"rguisot77@answers.com"},
{"id":261,"first_name":"Maudie","last_name":"Fakeley","email":"mfakeley78@vinaora.com"},
{"id":262,"first_name":"King","last_name":"Andriulis","email":"kandriulis79@tinypic.com"},
{"id":263,"first_name":"Ximenez","last_name":"Enden","email":"xenden7a@samsung.com"},
{"id":264,"first_name":"Gawen","last_name":"Jouning","email":"gjouning7b@smh.com.au"},
{"id":265,"first_name":"Redford","last_name":"Dinan","email":"rdinan7c@i2i.jp"},
{"id":266,"first_name":"Madelaine","last_name":"MacPherson","email":"mmacpherson7d@newsvine.com"},
{"id":267,"first_name":"Laryssa","last_name":"Clemintoni","email":"lclemintoni7e@webeden.co.uk"},
{"id":268,"first_name":"Emmalynn","last_name":"Purchase","email":"epurchase7f@hatena.ne.jp"},
{"id":269,"first_name":"Laurie","last_name":"Johansson","email":"ljohansson7g@i2i.jp"},
{"id":270,"first_name":"Kristoforo","last_name":"Eplett","email":"keplett7h@etsy.com"},
{"id":271,"first_name":"Mitzi","last_name":"Oldred","email":"moldred7i@imgur.com"},
{"id":272,"first_name":"Samantha","last_name":"Beverstock","email":"sbeverstock7j@ihg.com"},
{"id":273,"first_name":"Tiffy","last_name":"Tolmie","email":"ttolmie7k@dmoz.org"},
{"id":274,"first_name":"Arnuad","last_name":"Winn","email":"awinn7l@geocities.com"},
{"id":275,"first_name":"Lilla","last_name":"Gorst","email":"lgorst7m@soundcloud.com"},
{"id":276,"first_name":"Phelia","last_name":"Kisbey","email":"pkisbey7n@macromedia.com"},
{"id":277,"first_name":"Scarface","last_name":"Ubsdell","email":"subsdell7o@ovh.net"},
{"id":278,"first_name":"Stavro","last_name":"Rossoni","email":"srossoni7p@diigo.com"},
{"id":279,"first_name":"Eran","last_name":"Steiner","email":"esteiner7q@parallels.com"},
{"id":280,"first_name":"Carmina","last_name":"Bergstram","email":"cbergstram7r@independent.co.uk"},
{"id":281,"first_name":"Bernardina","last_name":"Foch","email":"bfoch7s@edublogs.org"},
{"id":282,"first_name":"Beverlee","last_name":"Delepine","email":"bdelepine7t@thetimes.co.uk"},
{"id":283,"first_name":"Arni","last_name":"Kester","email":"akester7u@bbb.org"},
{"id":284,"first_name":"Winona","last_name":"Nannetti","email":"wnannetti7v@oracle.com"},
{"id":285,"first_name":"Lenee","last_name":"Domotor","email":"ldomotor7w@upenn.edu"},
{"id":286,"first_name":"Nerty","last_name":"Lomis","email":"nlomis7x@google.it"},
{"id":287,"first_name":"Hally","last_name":"Geertje","email":"hgeertje7y@addtoany.com"},
{"id":288,"first_name":"Tabb","last_name":"McKenny","email":"tmckenny7z@cmu.edu"},
{"id":289,"first_name":"Shellysheldon","last_name":"Downton","email":"sdownton80@umich.edu"},
{"id":290,"first_name":"Catarina","last_name":"Oleksinski","email":"coleksinski81@icio.us"},
{"id":291,"first_name":"Katya","last_name":"Laye","email":"klaye82@bloglovin.com"},
{"id":292,"first_name":"Cosette","last_name":"Weir","email":"cweir83@ucsd.edu"},
{"id":293,"first_name":"Kimball","last_name":"Gaspar","email":"kgaspar84@fema.gov"},
{"id":294,"first_name":"Bobbie","last_name":"Hanley","email":"bhanley85@nytimes.com"},
{"id":295,"first_name":"Gifford","last_name":"Ballaam","email":"gballaam86@e-recht24.de"},
{"id":296,"first_name":"Sayers","last_name":"Catterall","email":"scatterall87@adobe.com"},
{"id":297,"first_name":"Josepha","last_name":"Lauthian","email":"jlauthian88@symantec.com"},
{"id":298,"first_name":"Wittie","last_name":"Lievesley","email":"wlievesley89@unc.edu"},
{"id":299,"first_name":"Gaspar","last_name":"Nolleau","email":"gnolleau8a@ustream.tv"},
{"id":300,"first_name":"Hall","last_name":"Ruffy","email":"hruffy8b@rambler.ru"},
{"id":301,"first_name":"Averil","last_name":"Jirik","email":"ajirik8c@youtu.be"},
{"id":302,"first_name":"Christen","last_name":"Splevings","email":"csplevings8d@opera.com"},
{"id":303,"first_name":"Klarrisa","last_name":"Balshaw","email":"kbalshaw8e@ning.com"},
{"id":304,"first_name":"Leigha","last_name":"Jobb","email":"ljobb8f@senate.gov"},
{"id":305,"first_name":"Hank","last_name":"Wickins","email":"hwickins8g@ed.gov"},
{"id":306,"first_name":"Cassondra","last_name":"Fellon","email":"cfellon8h@marriott.com"},
{"id":307,"first_name":"Giana","last_name":"Haruard","email":"gharuard8i@theglobeandmail.com"},
{"id":308,"first_name":"Georgiana","last_name":"Webster","email":"gwebster8j@china.com.cn"},
{"id":309,"first_name":"Lissy","last_name":"Treher","email":"ltreher8k@indiatimes.com"},
{"id":310,"first_name":"Abagail","last_name":"Fairleigh","email":"afairleigh8l@ox.ac.uk"},
{"id":311,"first_name":"Asia","last_name":"Lyburn","email":"alyburn8m@google.com.br"},
{"id":312,"first_name":"Becka","last_name":"Garthland","email":"bgarthland8n@sun.com"},
{"id":313,"first_name":"Thorstein","last_name":"Signori","email":"tsignori8o@chron.com"},
{"id":314,"first_name":"Linnie","last_name":"Sandeman","email":"lsandeman8p@un.org"},
{"id":315,"first_name":"Horatius","last_name":"Edridge","email":"hedridge8q@delicious.com"},
{"id":316,"first_name":"Theo","last_name":"Pattini","email":"tpattini8r@miibeian.gov.cn"},
{"id":317,"first_name":"Wilone","last_name":"Tolerton","email":"wtolerton8s@kickstarter.com"},
{"id":318,"first_name":"Balduin","last_name":"Wardhough","email":"bwardhough8t@nydailynews.com"},
{"id":319,"first_name":"Jerrie","last_name":"Markussen","email":"jmarkussen8u@google.nl"},
{"id":320,"first_name":"Michelle","last_name":"Pashler","email":"mpashler8v@g.co"},
{"id":321,"first_name":"Cristobal","last_name":"Meneo","email":"cmeneo8w@ucoz.ru"},
{"id":322,"first_name":"Gaynor","last_name":"Toffel","email":"gtoffel8x@theglobeandmail.com"},
{"id":323,"first_name":"Evvie","last_name":"Fendley","email":"efendley8y@jalbum.net"},
{"id":324,"first_name":"Cornelia","last_name":"Whatham","email":"cwhatham8z@google.de"},
{"id":325,"first_name":"El","last_name":"Daft","email":"edaft90@noaa.gov"},
{"id":326,"first_name":"Lesley","last_name":"Chopy","email":"lchopy91@geocities.com"},
{"id":327,"first_name":"Shelagh","last_name":"Notton","email":"snotton92@de.vu"},
{"id":328,"first_name":"Dani","last_name":"Caygill","email":"dcaygill93@slideshare.net"},
{"id":329,"first_name":"Elmira","last_name":"Sawdon","email":"esawdon94@berkeley.edu"},
{"id":330,"first_name":"Phyllida","last_name":"Camellini","email":"pcamellini95@fema.gov"},
{"id":331,"first_name":"Leonardo","last_name":"Whitaker","email":"lwhitaker96@amazon.co.uk"},
{"id":332,"first_name":"Vasili","last_name":"Strutton","email":"vstrutton97@ask.com"},
{"id":333,"first_name":"Maurise","last_name":"Beaudry","email":"mbeaudry98@opera.com"},
{"id":334,"first_name":"Hollis","last_name":"Olligan","email":"holligan99@hud.gov"},
{"id":335,"first_name":"Stevana","last_name":"Treneer","email":"streneer9a@networksolutions.com"},
{"id":336,"first_name":"Norton","last_name":"Hampshaw","email":"nhampshaw9b@bluehost.com"},
{"id":337,"first_name":"Siffre","last_name":"Saywood","email":"ssaywood9c@ning.com"},
{"id":338,"first_name":"Giavani","last_name":"Borne","email":"gborne9d@alibaba.com"},
{"id":339,"first_name":"Sacha","last_name":"Stollsteimer","email":"sstollsteimer9e@jugem.jp"},
{"id":340,"first_name":"Tucky","last_name":"Grocott","email":"tgrocott9f@wikia.com"},
{"id":341,"first_name":"Jennifer","last_name":"Devigne","email":"jdevigne9g@a8.net"},
{"id":342,"first_name":"Lenard","last_name":"Barsby","email":"lbarsby9h@mlb.com"},
{"id":343,"first_name":"Adrian","last_name":"Lampkin","email":"alampkin9i@sbwire.com"},
{"id":344,"first_name":"Lewes","last_name":"Betho","email":"lbetho9j@cdc.gov"},
{"id":345,"first_name":"Lazar","last_name":"Estcourt","email":"lestcourt9k@amazonaws.com"},
{"id":346,"first_name":"Jeannie","last_name":"Morfey","email":"jmorfey9l@wikispaces.com"},
{"id":347,"first_name":"Chiquia","last_name":"Orrow","email":"corrow9m@irs.gov"},
{"id":348,"first_name":"Michaeline","last_name":"Overpool","email":"moverpool9n@tripadvisor.com"},
{"id":349,"first_name":"Bettye","last_name":"Whaites","email":"bwhaites9o@mit.edu"},
{"id":350,"first_name":"Nicky","last_name":"Goulbourn","email":"ngoulbourn9p@devhub.com"},
{"id":351,"first_name":"Chandal","last_name":"Botright","email":"cbotright9q@qq.com"},
{"id":352,"first_name":"Shelby","last_name":"Gaythorpe","email":"sgaythorpe9r@cbc.ca"},
{"id":353,"first_name":"Artus","last_name":"Tregoning","email":"atregoning9s@hexun.com"},
{"id":354,"first_name":"Aloysius","last_name":"Bennion","email":"abennion9t@slideshare.net"},
{"id":355,"first_name":"Mischa","last_name":"St. Pierre","email":"mstpierre9u@time.com"},
{"id":356,"first_name":"Etienne","last_name":"Macguire","email":"emacguire9v@feedburner.com"},
{"id":357,"first_name":"Birgitta","last_name":"Foxley","email":"bfoxley9w@apache.org"},
{"id":358,"first_name":"Leticia","last_name":"Blanchflower","email":"lblanchflower9x@behance.net"},
{"id":359,"first_name":"Rhea","last_name":"Raun","email":"rraun9y@statcounter.com"},
{"id":360,"first_name":"Row","last_name":"Mickleborough","email":"rmickleborough9z@networkadvertising.org"},
{"id":361,"first_name":"Bail","last_name":"Jarlmann","email":"bjarlmanna0@nymag.com"},
{"id":362,"first_name":"Collette","last_name":"Blackah","email":"cblackaha1@instagram.com"},
{"id":363,"first_name":"Cayla","last_name":"Peto","email":"cpetoa2@google.es"},
{"id":364,"first_name":"Annmarie","last_name":"Derham","email":"aderhama3@paginegialle.it"},
{"id":365,"first_name":"Vick","last_name":"Strutt","email":"vstrutta4@linkedin.com"},
{"id":366,"first_name":"Joby","last_name":"Gowans","email":"jgowansa5@nih.gov"},
{"id":367,"first_name":"Ortensia","last_name":"Beake","email":"obeakea6@geocities.com"},
{"id":368,"first_name":"Maighdiln","last_name":"Gwilym","email":"mgwilyma7@webs.com"},
{"id":369,"first_name":"Irwin","last_name":"Lawrenson","email":"ilawrensona8@amazon.de"},
{"id":370,"first_name":"Lavena","last_name":"Duinbleton","email":"lduinbletona9@soup.io"},
{"id":371,"first_name":"Bertie","last_name":"Sanchez","email":"bsanchezaa@amazon.co.jp"},
{"id":372,"first_name":"Liam","last_name":"O'Nion","email":"lonionab@symantec.com"},
{"id":373,"first_name":"Elsinore","last_name":"Joinsey","email":"ejoinseyac@vimeo.com"},
{"id":374,"first_name":"Tallulah","last_name":"Mowbray","email":"tmowbrayad@ebay.co.uk"},
{"id":375,"first_name":"Nelli","last_name":"Knotton","email":"nknottonae@foxnews.com"},
{"id":376,"first_name":"Camila","last_name":"Rummings","email":"crummingsaf@forbes.com"},
{"id":377,"first_name":"Alonzo","last_name":"Peek","email":"apeekag@wisc.edu"},
{"id":378,"first_name":"Evelyn","last_name":"Gladden","email":"egladdenah@europa.eu"},
{"id":379,"first_name":"Miguel","last_name":"Mourton","email":"mmourtonai@sfgate.com"},
{"id":380,"first_name":"Colly","last_name":"Dybell","email":"cdybellaj@newsvine.com"},
{"id":381,"first_name":"Otis","last_name":"Brightwell","email":"obrightwellak@weibo.com"},
{"id":382,"first_name":"Lou","last_name":"Killingback","email":"lkillingbackal@reverbnation.com"},
{"id":383,"first_name":"Betsey","last_name":"Van Arsdale","email":"bvanarsdaleam@wordpress.org"},
{"id":384,"first_name":"Monique","last_name":"Bretland","email":"mbretlandan@jimdo.com"},
{"id":385,"first_name":"Giacinta","last_name":"Savatier","email":"gsavatierao@bbc.co.uk"},
{"id":386,"first_name":"Demetris","last_name":"Loughlan","email":"dloughlanap@boston.com"},
{"id":387,"first_name":"Anstice","last_name":"Baitman","email":"abaitmanaq@google.com.au"},
{"id":388,"first_name":"Margot","last_name":"Bariball","email":"mbariballar@google.com.au"},
{"id":389,"first_name":"Jillie","last_name":"Oakly","email":"joaklyas@addtoany.com"},
{"id":390,"first_name":"Haven","last_name":"Somerton","email":"hsomertonat@is.gd"},
{"id":391,"first_name":"Yance","last_name":"Wootton","email":"ywoottonau@blogtalkradio.com"},
{"id":392,"first_name":"Christian","last_name":"Cake","email":"ccakeav@4shared.com"},
{"id":393,"first_name":"Erhard","last_name":"Forrest","email":"eforrestaw@biglobe.ne.jp"},
{"id":394,"first_name":"Wileen","last_name":"Heam","email":"wheamax@google.com.hk"},
{"id":395,"first_name":"Burg","last_name":"Lodo","email":"blodoay@plala.or.jp"},
{"id":396,"first_name":"Innis","last_name":"Dicte","email":"idicteaz@oaic.gov.au"},
{"id":397,"first_name":"Stern","last_name":"Blamphin","email":"sblamphinb0@fema.gov"},
{"id":398,"first_name":"Melodie","last_name":"Pieter","email":"mpieterb1@webeden.co.uk"},
{"id":399,"first_name":"Abbey","last_name":"Wrotham","email":"awrothamb2@feedburner.com"},
{"id":400,"first_name":"Lacey","last_name":"Sallans","email":"lsallansb3@canalblog.com"},
{"id":401,"first_name":"Gloriane","last_name":"Coalburn","email":"gcoalburnb4@answers.com"},
{"id":402,"first_name":"Joey","last_name":"Hampstead","email":"jhampsteadb5@berkeley.edu"},
{"id":403,"first_name":"Alvera","last_name":"Pikett","email":"apikettb6@dell.com"},
{"id":404,"first_name":"Ellswerth","last_name":"Idle","email":"eidleb7@japanpost.jp"},
{"id":405,"first_name":"Carmelle","last_name":"Townsend","email":"ctownsendb8@msn.com"},
{"id":406,"first_name":"Wakefield","last_name":"Volette","email":"wvoletteb9@nih.gov"},
{"id":407,"first_name":"Ham","last_name":"Coade","email":"hcoadeba@toplist.cz"},
{"id":408,"first_name":"Danice","last_name":"Petriello","email":"dpetriellobb@tripadvisor.com"},
{"id":409,"first_name":"Talbot","last_name":"Dossit","email":"tdossitbc@yandex.ru"},
{"id":410,"first_name":"Thorin","last_name":"Gercke","email":"tgerckebd@walmart.com"},
{"id":411,"first_name":"Andy","last_name":"Ommanney","email":"aommanneybe@google.co.jp"},
{"id":412,"first_name":"Konstantin","last_name":"Boyson","email":"kboysonbf@google.nl"},
{"id":413,"first_name":"Marylou","last_name":"Buckney","email":"mbuckneybg@flavors.me"},
{"id":414,"first_name":"Danette","last_name":"Corbett","email":"dcorbettbh@dmoz.org"},
{"id":415,"first_name":"Bran","last_name":"Erangey","email":"berangeybi@hud.gov"},
{"id":416,"first_name":"Lucia","last_name":"Goosey","email":"lgooseybj@shutterfly.com"},
{"id":417,"first_name":"Cacilie","last_name":"Gilluley","email":"cgilluleybk@craigslist.org"},
{"id":418,"first_name":"Zeke","last_name":"Necolds","email":"znecoldsbl@amazon.com"},
{"id":419,"first_name":"Rollie","last_name":"Lillywhite","email":"rlillywhitebm@yale.edu"},
{"id":420,"first_name":"Hamid","last_name":"Cousens","email":"hcousensbn@lycos.com"},
{"id":421,"first_name":"Vinson","last_name":"Donavan","email":"vdonavanbo@mail.ru"},
{"id":422,"first_name":"Rakel","last_name":"Knowling","email":"rknowlingbp@canalblog.com"},
{"id":423,"first_name":"Fritz","last_name":"Blakeston","email":"fblakestonbq@cnn.com"},
{"id":424,"first_name":"Alvan","last_name":"Schelle","email":"aschellebr@mysql.com"},
{"id":425,"first_name":"Johanna","last_name":"Legat","email":"jlegatbs@technorati.com"},
{"id":426,"first_name":"Creighton","last_name":"Belcham","email":"cbelchambt@about.com"},
{"id":427,"first_name":"Philly","last_name":"Wannell","email":"pwannellbu@indiatimes.com"},
{"id":428,"first_name":"Vivie","last_name":"Byrom","email":"vbyrombv@networkadvertising.org"},
{"id":429,"first_name":"Ange","last_name":"Ughelli","email":"aughellibw@1688.com"},
{"id":430,"first_name":"Charyl","last_name":"Fulbrook","email":"cfulbrookbx@com.com"},
{"id":431,"first_name":"Barnie","last_name":"Brabender","email":"bbrabenderby@patch.com"},
{"id":432,"first_name":"Sarette","last_name":"Nayshe","email":"snayshebz@sina.com.cn"},
{"id":433,"first_name":"Korie","last_name":"Gullis","email":"kgullisc0@gizmodo.com"},
{"id":434,"first_name":"Sibbie","last_name":"Colyer","email":"scolyerc1@europa.eu"},
{"id":435,"first_name":"Elysha","last_name":"Elgey","email":"eelgeyc2@mozilla.org"},
{"id":436,"first_name":"Goddard","last_name":"Barnwall","email":"gbarnwallc3@163.com"},
{"id":437,"first_name":"Theodora","last_name":"Palfery","email":"tpalferyc4@gravatar.com"},
{"id":438,"first_name":"Harlan","last_name":"Lerego","email":"hleregoc5@dyndns.org"},
{"id":439,"first_name":"Sascha","last_name":"Hartburn","email":"shartburnc6@cnn.com"},
{"id":440,"first_name":"Cointon","last_name":"O'Hingerty","email":"cohingertyc7@dell.com"},
{"id":441,"first_name":"Eileen","last_name":"MacBain","email":"emacbainc8@eventbrite.com"},
{"id":442,"first_name":"Jimmie","last_name":"Lippett","email":"jlippettc9@live.com"},
{"id":443,"first_name":"Minna","last_name":"Rattray","email":"mrattrayca@census.gov"},
{"id":444,"first_name":"Dottie","last_name":"McAuslene","email":"dmcauslenecb@gizmodo.com"},
{"id":445,"first_name":"Wilbert","last_name":"Gilfoyle","email":"wgilfoylecc@theatlantic.com"},
{"id":446,"first_name":"Yorgos","last_name":"Nannetti","email":"ynannetticd@rakuten.co.jp"},
{"id":447,"first_name":"Clementius","last_name":"Killingworth","email":"ckillingworthce@flickr.com"},
{"id":448,"first_name":"Turner","last_name":"Malyan","email":"tmalyancf@is.gd"},
{"id":449,"first_name":"Nicolais","last_name":"Sirl","email":"nsirlcg@ox.ac.uk"},
{"id":450,"first_name":"Imogene","last_name":"Kynoch","email":"ikynochch@google.com.br"},
{"id":451,"first_name":"Faye","last_name":"Crampton","email":"fcramptonci@infoseek.co.jp"},
{"id":452,"first_name":"Giana","last_name":"Port","email":"gportcj@auda.org.au"},
{"id":453,"first_name":"Tracie","last_name":"Martins","email":"tmartinsck@who.int"},
{"id":454,"first_name":"Ophelia","last_name":"Ceschelli","email":"oceschellicl@edublogs.org"},
{"id":455,"first_name":"Kaia","last_name":"Kench","email":"kkenchcm@wiley.com"},
{"id":456,"first_name":"Theodoric","last_name":"Soares","email":"tsoarescn@weibo.com"},
{"id":457,"first_name":"Jephthah","last_name":"Speechley","email":"jspeechleyco@harvard.edu"},
{"id":458,"first_name":"Jean","last_name":"Candwell","email":"jcandwellcp@miibeian.gov.cn"},
{"id":459,"first_name":"Chan","last_name":"Innocenti","email":"cinnocenticq@hostgator.com"},
{"id":460,"first_name":"Valentia","last_name":"Snape","email":"vsnapecr@zimbio.com"},
{"id":461,"first_name":"Lauretta","last_name":"Kupper","email":"lkuppercs@ebay.co.uk"},
{"id":462,"first_name":"Hal","last_name":"Maberley","email":"hmaberleyct@nature.com"},
{"id":463,"first_name":"Filide","last_name":"Bowker","email":"fbowkercu@nhs.uk"},
{"id":464,"first_name":"Allen","last_name":"Purves","email":"apurvescv@g.co"},
{"id":465,"first_name":"Corinne","last_name":"Fallowes","email":"cfallowescw@mlb.com"},
{"id":466,"first_name":"Anthe","last_name":"Theunissen","email":"atheunissencx@livejournal.com"},
{"id":467,"first_name":"Jeanie","last_name":"Gallehock","email":"jgallehockcy@discuz.net"},
{"id":468,"first_name":"Aluino","last_name":"Josovitz","email":"ajosovitzcz@yellowbook.com"},
{"id":469,"first_name":"Krisha","last_name":"Najafian","email":"knajafiand0@reverbnation.com"},
{"id":470,"first_name":"Flynn","last_name":"Thinn","email":"fthinnd1@spiegel.de"},
{"id":471,"first_name":"Gris","last_name":"Dayton","email":"gdaytond2@oracle.com"},
{"id":472,"first_name":"Rina","last_name":"McGloin","email":"rmcgloind3@indiegogo.com"},
{"id":473,"first_name":"Yvor","last_name":"Crone","email":"ycroned4@yellowbook.com"},
{"id":474,"first_name":"Roland","last_name":"Loughrey","email":"rloughreyd5@dell.com"},
{"id":475,"first_name":"Dario","last_name":"Elies","email":"deliesd6@intel.com"},
{"id":476,"first_name":"Brodie","last_name":"Ager","email":"bagerd7@reverbnation.com"},
{"id":477,"first_name":"Sayres","last_name":"Shimoni","email":"sshimonid8@lulu.com"},
{"id":478,"first_name":"Pascal","last_name":"Bolton","email":"pboltond9@yolasite.com"},
{"id":479,"first_name":"Rafaela","last_name":"Ottey","email":"rotteyda@cdbaby.com"},
{"id":480,"first_name":"Devlin","last_name":"Foddy","email":"dfoddydb@1688.com"},
{"id":481,"first_name":"Koressa","last_name":"Inkster","email":"kinksterdc@biglobe.ne.jp"},
{"id":482,"first_name":"Gwendolen","last_name":"Goodayle","email":"ggoodayledd@redcross.org"},
{"id":483,"first_name":"Ronnie","last_name":"Francklyn","email":"rfrancklynde@bravesites.com"},
{"id":484,"first_name":"Sidonia","last_name":"Wildblood","email":"swildblooddf@goodreads.com"},
{"id":485,"first_name":"Tabor","last_name":"Scapens","email":"tscapensdg@wikipedia.org"},
{"id":486,"first_name":"Ky","last_name":"Rockcliffe","email":"krockcliffedh@princeton.edu"},
{"id":487,"first_name":"Jordon","last_name":"Kelsey","email":"jkelseydi@nhs.uk"},
{"id":488,"first_name":"Enrica","last_name":"McCalister","email":"emccalisterdj@marketwatch.com"},
{"id":489,"first_name":"Hillel","last_name":"Mitkcov","email":"hmitkcovdk@narod.ru"},
{"id":490,"first_name":"Brianna","last_name":"Josephson","email":"bjosephsondl@google.com.au"},
{"id":491,"first_name":"Stoddard","last_name":"Manley","email":"smanleydm@hexun.com"},
{"id":492,"first_name":"Georges","last_name":"Gumery","email":"ggumerydn@loc.gov"},
{"id":493,"first_name":"Zach","last_name":"Goodread","email":"zgoodreaddo@shutterfly.com"},
{"id":494,"first_name":"Stella","last_name":"Kares","email":"skaresdp@hc360.com"},
{"id":495,"first_name":"Miguela","last_name":"Kensit","email":"mkensitdq@edublogs.org"},
{"id":496,"first_name":"Doe","last_name":"Sharkey","email":"dsharkeydr@list-manage.com"},
{"id":497,"first_name":"Erina","last_name":"Aiken","email":"eaikends@wired.com"},
{"id":498,"first_name":"Charline","last_name":"Maseres","email":"cmaseresdt@amazonaws.com"},
{"id":499,"first_name":"Ddene","last_name":"Graveston","email":"dgravestondu@webnode.com"},
{"id":500,"first_name":"Freemon","last_name":"Jenno","email":"fjennodv@domainmarket.com"},
{"id":501,"first_name":"Devlen","last_name":"Labbe","email":"dlabbedw@is.gd"},
{"id":502,"first_name":"Trey","last_name":"Nials","email":"tnialsdx@hatena.ne.jp"},
{"id":503,"first_name":"Faith","last_name":"Duff","email":"fduffdy@t-online.de"},
{"id":504,"first_name":"Noami","last_name":"Dyer","email":"ndyerdz@paginegialle.it"},
{"id":505,"first_name":"Spike","last_name":"Gierck","email":"sgiercke0@zimbio.com"},
{"id":506,"first_name":"Germana","last_name":"Lundbech","email":"glundbeche1@github.io"},
{"id":507,"first_name":"Artur","last_name":"Palethorpe","email":"apalethorpee2@vkontakte.ru"},
{"id":508,"first_name":"Roxie","last_name":"Beceril","email":"rbecerile3@wikispaces.com"},
{"id":509,"first_name":"Nessie","last_name":"Klulik","email":"nklulike4@1und1.de"},
{"id":510,"first_name":"Rosana","last_name":"Wybron","email":"rwybrone5@washington.edu"},
{"id":511,"first_name":"Edlin","last_name":"Blaisdale","email":"eblaisdalee6@merriam-webster.com"},
{"id":512,"first_name":"Tedi","last_name":"Darrington","email":"tdarringtone7@xing.com"},
{"id":513,"first_name":"Calv","last_name":"Whittles","email":"cwhittlese8@reddit.com"},
{"id":514,"first_name":"Mersey","last_name":"Binnie","email":"mbinniee9@wikipedia.org"},
{"id":515,"first_name":"Adamo","last_name":"Savary","email":"asavaryea@cafepress.com"},
{"id":516,"first_name":"Lauritz","last_name":"McGarahan","email":"lmcgarahaneb@hhs.gov"},
{"id":517,"first_name":"Dunn","last_name":"Skoate","email":"dskoateec@tinyurl.com"},
{"id":518,"first_name":"Jeniffer","last_name":"Penwright","email":"jpenwrighted@java.com"},
{"id":519,"first_name":"Kylen","last_name":"Durdle","email":"kdurdleee@npr.org"},
{"id":520,"first_name":"Gardie","last_name":"Vatini","email":"gvatinief@berkeley.edu"},
{"id":521,"first_name":"Antonella","last_name":"Wibrew","email":"awibreweg@tinyurl.com"},
{"id":522,"first_name":"Melany","last_name":"Oxlade","email":"moxladeeh@csmonitor.com"},
{"id":523,"first_name":"Hayyim","last_name":"Hanney","email":"hhanneyei@constantcontact.com"},
{"id":524,"first_name":"Marya","last_name":"Barlie","email":"mbarlieej@oracle.com"},
{"id":525,"first_name":"Kayne","last_name":"Scriviner","email":"kscrivinerek@woothemes.com"},
{"id":526,"first_name":"Niels","last_name":"Teale","email":"ntealeel@princeton.edu"},
{"id":527,"first_name":"Griz","last_name":"McCuish","email":"gmccuishem@so-net.ne.jp"},
{"id":528,"first_name":"Wilie","last_name":"Hatto","email":"whattoen@usnews.com"},
{"id":529,"first_name":"Carlynn","last_name":"MacLeese","email":"cmacleeseeo@instagram.com"},
{"id":530,"first_name":"Ollie","last_name":"Tildesley","email":"otildesleyep@princeton.edu"},
{"id":531,"first_name":"Edita","last_name":"Masser","email":"emassereq@hexun.com"},
{"id":532,"first_name":"Seana","last_name":"Fisby","email":"sfisbyer@answers.com"},
{"id":533,"first_name":"Gradey","last_name":"Casero","email":"gcaseroes@amazon.co.uk"},
{"id":534,"first_name":"Rivalee","last_name":"Wrankmore","email":"rwrankmoreet@about.me"},
{"id":535,"first_name":"Garald","last_name":"Cofax","email":"gcofaxeu@ameblo.jp"},
{"id":536,"first_name":"Stesha","last_name":"Gladbach","email":"sgladbachev@businessweek.com"},
{"id":537,"first_name":"Dasya","last_name":"Vellender","email":"dvellenderew@t.co"},
{"id":538,"first_name":"Katrina","last_name":"Dongall","email":"kdongallex@marriott.com"},
{"id":539,"first_name":"Jefferson","last_name":"Rawsthorne","email":"jrawsthorneey@mozilla.com"},
{"id":540,"first_name":"Reed","last_name":"Whiffin","email":"rwhiffinez@trellian.com"},
{"id":541,"first_name":"Tomi","last_name":"Korejs","email":"tkorejsf0@comcast.net"},
{"id":542,"first_name":"Marlowe","last_name":"McLagan","email":"mmclaganf1@npr.org"},
{"id":543,"first_name":"Alessandra","last_name":"Shucksmith","email":"ashucksmithf2@abc.net.au"},
{"id":544,"first_name":"Pamella","last_name":"Huard","email":"phuardf3@businessweek.com"},
{"id":545,"first_name":"Manda","last_name":"Ivanyutin","email":"mivanyutinf4@seattletimes.com"},
{"id":546,"first_name":"Karna","last_name":"Sorrie","email":"ksorrief5@mediafire.com"},
{"id":547,"first_name":"Sanson","last_name":"Penvarden","email":"spenvardenf6@mit.edu"},
{"id":548,"first_name":"Jeane","last_name":"Espinal","email":"jespinalf7@gmpg.org"},
{"id":549,"first_name":"Sherye","last_name":"Birtwhistle","email":"sbirtwhistlef8@wired.com"},
{"id":550,"first_name":"Oswell","last_name":"Dellow","email":"odellowf9@unicef.org"},
{"id":551,"first_name":"Salomo","last_name":"Billingham","email":"sbillinghamfa@cnbc.com"},
{"id":552,"first_name":"Jackqueline","last_name":"Folks","email":"jfolksfb@hao123.com"},
{"id":553,"first_name":"Gunner","last_name":"Yankin","email":"gyankinfc@blogspot.com"},
{"id":554,"first_name":"Charlotta","last_name":"Dy","email":"cdyfd@imgur.com"},
{"id":555,"first_name":"Teador","last_name":"Etteridge","email":"tetteridgefe@umn.edu"},
{"id":556,"first_name":"Rebe","last_name":"O'Ferris","email":"roferrisff@i2i.jp"},
{"id":557,"first_name":"Adams","last_name":"Norgan","email":"anorganfg@boston.com"},
{"id":558,"first_name":"Robinson","last_name":"Pesticcio","email":"rpesticciofh@blog.com"},
{"id":559,"first_name":"Hercule","last_name":"Carsey","email":"hcarseyfi@arstechnica.com"},
{"id":560,"first_name":"Mordy","last_name":"Jenoure","email":"mjenourefj@smh.com.au"},
{"id":561,"first_name":"Zonnya","last_name":"Surmon","email":"zsurmonfk@gnu.org"},
{"id":562,"first_name":"Edgard","last_name":"Pamment","email":"epammentfl@ezinearticles.com"},
{"id":563,"first_name":"Hadlee","last_name":"Kasting","email":"hkastingfm@smh.com.au"},
{"id":564,"first_name":"Brew","last_name":"Tommasi","email":"btommasifn@google.it"},
{"id":565,"first_name":"Betta","last_name":"Reddington","email":"breddingtonfo@diigo.com"},
{"id":566,"first_name":"Dosi","last_name":"Dimberline","email":"ddimberlinefp@dailymail.co.uk"},
{"id":567,"first_name":"Gwendolen","last_name":"Molson","email":"gmolsonfq@huffingtonpost.com"},
{"id":568,"first_name":"Viviyan","last_name":"Fernan","email":"vfernanfr@acquirethisname.com"},
{"id":569,"first_name":"Eleonore","last_name":"Issacson","email":"eissacsonfs@icio.us"},
{"id":570,"first_name":"Hagen","last_name":"Lowfill","email":"hlowfillft@canalblog.com"},
{"id":571,"first_name":"Eugenie","last_name":"Boller","email":"ebollerfu@phoca.cz"},
{"id":572,"first_name":"Ozzie","last_name":"Suttaby","email":"osuttabyfv@i2i.jp"},
{"id":573,"first_name":"Doralynn","last_name":"Bollins","email":"dbollinsfw@sourceforge.net"},
{"id":574,"first_name":"Drew","last_name":"Grundon","email":"dgrundonfx@imageshack.us"},
{"id":575,"first_name":"Elsie","last_name":"Quilligan","email":"equilliganfy@trellian.com"},
{"id":576,"first_name":"Zorina","last_name":"Zorzini","email":"zzorzinifz@answers.com"},
{"id":577,"first_name":"Sumner","last_name":"Pocock","email":"spocockg0@joomla.org"},
{"id":578,"first_name":"Isidora","last_name":"de Pinna","email":"idepinnag1@boston.com"},
{"id":579,"first_name":"Rab","last_name":"Marages","email":"rmaragesg2@fda.gov"},
{"id":580,"first_name":"Roseanna","last_name":"Cherry","email":"rcherryg3@ning.com"},
{"id":581,"first_name":"Neila","last_name":"Rickerd","email":"nrickerdg4@sciencedaily.com"},
{"id":582,"first_name":"Perry","last_name":"Klassman","email":"pklassmang5@hubpages.com"},
{"id":583,"first_name":"Marchelle","last_name":"Siggers","email":"msiggersg6@illinois.edu"},
{"id":584,"first_name":"Jeremie","last_name":"Dougharty","email":"jdoughartyg7@wix.com"},
{"id":585,"first_name":"Hatti","last_name":"Sandbatch","email":"hsandbatchg8@usda.gov"},
{"id":586,"first_name":"Bobette","last_name":"Dyer","email":"bdyerg9@mediafire.com"},
{"id":587,"first_name":"Winnie","last_name":"Kersley","email":"wkersleyga@spotify.com"},
{"id":588,"first_name":"Benedict","last_name":"Ebourne","email":"bebournegb@europa.eu"},
{"id":589,"first_name":"Atalanta","last_name":"Chattington","email":"achattingtongc@illinois.edu"},
{"id":590,"first_name":"Korella","last_name":"Castell","email":"kcastellgd@who.int"},
{"id":591,"first_name":"Nydia","last_name":"Windress","email":"nwindressge@mail.ru"},
{"id":592,"first_name":"Waring","last_name":"Bonde","email":"wbondegf@reference.com"},
{"id":593,"first_name":"Enriqueta","last_name":"Froggatt","email":"efroggattgg@washington.edu"},
{"id":594,"first_name":"Craig","last_name":"Belsey","email":"cbelseygh@seattletimes.com"},
{"id":595,"first_name":"Aleda","last_name":"Robus","email":"arobusgi@google.de"},
{"id":596,"first_name":"Alleen","last_name":"Cope","email":"acopegj@ovh.net"},
{"id":597,"first_name":"Annabelle","last_name":"Stern","email":"asterngk@mozilla.com"},
{"id":598,"first_name":"Quintana","last_name":"Ledger","email":"qledgergl@storify.com"},
{"id":599,"first_name":"Hilario","last_name":"Chadband","email":"hchadbandgm@icq.com"},
{"id":600,"first_name":"Martyn","last_name":"Arnefield","email":"marnefieldgn@alexa.com"},
{"id":601,"first_name":"Alyse","last_name":"Filon","email":"afilongo@posterous.com"},
{"id":602,"first_name":"Addie","last_name":"Dixcey","email":"adixceygp@mozilla.com"},
{"id":603,"first_name":"Weider","last_name":"Freebury","email":"wfreeburygq@utexas.edu"},
{"id":604,"first_name":"Teddy","last_name":"Idill","email":"tidillgr@is.gd"},
{"id":605,"first_name":"Cary","last_name":"Abraham","email":"cabrahamgs@uiuc.edu"},
{"id":606,"first_name":"Reid","last_name":"Tribbeck","email":"rtribbeckgt@gravatar.com"},
{"id":607,"first_name":"Griffy","last_name":"Starcks","email":"gstarcksgu@slideshare.net"},
{"id":608,"first_name":"Allyce","last_name":"Sword","email":"aswordgv@cloudflare.com"},
{"id":609,"first_name":"Ardyth","last_name":"Mahood","email":"amahoodgw@boston.com"},
{"id":610,"first_name":"Cosme","last_name":"Judkins","email":"cjudkinsgx@omniture.com"},
{"id":611,"first_name":"Moise","last_name":"Holcroft","email":"mholcroftgy@amazon.co.jp"},
{"id":612,"first_name":"Horst","last_name":"Stowers","email":"hstowersgz@si.edu"},
{"id":613,"first_name":"Charo","last_name":"Fossitt","email":"cfossitth0@hud.gov"},
{"id":614,"first_name":"Cariotta","last_name":"Tesdale","email":"ctesdaleh1@umich.edu"},
{"id":615,"first_name":"Latrena","last_name":"Dradey","email":"ldradeyh2@salon.com"},
{"id":616,"first_name":"Cherry","last_name":"Bamfield","email":"cbamfieldh3@admin.ch"},
{"id":617,"first_name":"Elmo","last_name":"Velez","email":"evelezh4@simplemachines.org"},
{"id":618,"first_name":"Olenolin","last_name":"Middlemist","email":"omiddlemisth5@baidu.com"},
{"id":619,"first_name":"Arnold","last_name":"Trask","email":"atraskh6@cornell.edu"},
{"id":620,"first_name":"Clemente","last_name":"Dand","email":"cdandh7@smh.com.au"},
{"id":621,"first_name":"Sheff","last_name":"Lumbley","email":"slumbleyh8@hud.gov"},
{"id":622,"first_name":"Duffie","last_name":"Fenkel","email":"dfenkelh9@jugem.jp"},
{"id":623,"first_name":"Bay","last_name":"Gladman","email":"bgladmanha@weibo.com"},
{"id":624,"first_name":"Ezmeralda","last_name":"Scandwright","email":"escandwrighthb@pagesperso-orange.fr"},
{"id":625,"first_name":"Angeli","last_name":"Laughnan","email":"alaughnanhc@umn.edu"},
{"id":626,"first_name":"Moselle","last_name":"Balle","email":"mballehd@cloudflare.com"},
{"id":627,"first_name":"Livy","last_name":"Littledyke","email":"llittledykehe@phpbb.com"},
{"id":628,"first_name":"Salmon","last_name":"Gilding","email":"sgildinghf@apache.org"},
{"id":629,"first_name":"Aurelie","last_name":"Maccree","email":"amaccreehg@eepurl.com"},
{"id":630,"first_name":"Lauraine","last_name":"Cowmeadow","email":"lcowmeadowhh@reference.com"},
{"id":631,"first_name":"Raphaela","last_name":"Wem","email":"rwemhi@cloudflare.com"},
{"id":632,"first_name":"Cart","last_name":"Dillinger","email":"cdillingerhj@over-blog.com"},
{"id":633,"first_name":"Codee","last_name":"Cronshaw","email":"ccronshawhk@cmu.edu"},
{"id":634,"first_name":"Amanda","last_name":"Saphin","email":"asaphinhl@hibu.com"},
{"id":635,"first_name":"Aloin","last_name":"Izaks","email":"aizakshm@edublogs.org"},
{"id":636,"first_name":"Carry","last_name":"Pozzo","email":"cpozzohn@vimeo.com"},
{"id":637,"first_name":"Kayle","last_name":"Taunton","email":"ktauntonho@upenn.edu"},
{"id":638,"first_name":"Chrissy","last_name":"Janney","email":"cjanneyhp@hud.gov"},
{"id":639,"first_name":"Ardyth","last_name":"Farreil","email":"afarreilhq@theglobeandmail.com"},
{"id":640,"first_name":"Ingaborg","last_name":"Imloch","email":"iimlochhr@cisco.com"},
{"id":641,"first_name":"Mead","last_name":"Baynam","email":"mbaynamhs@whitehouse.gov"},
{"id":642,"first_name":"Heidie","last_name":"Gillmor","email":"hgillmorht@w3.org"},
{"id":643,"first_name":"Benson","last_name":"Van Driel","email":"bvandrielhu@diigo.com"},
{"id":644,"first_name":"Bethanne","last_name":"Luther","email":"blutherhv@marriott.com"},
{"id":645,"first_name":"Susann","last_name":"Larive","email":"slarivehw@ucla.edu"},
{"id":646,"first_name":"Ingeborg","last_name":"Dafforne","email":"idaffornehx@studiopress.com"},
{"id":647,"first_name":"Ravi","last_name":"Benduhn","email":"rbenduhnhy@163.com"},
{"id":648,"first_name":"Germayne","last_name":"Carff","email":"gcarffhz@hugedomains.com"},
{"id":649,"first_name":"Prent","last_name":"Vidyapin","email":"pvidyapini0@blogger.com"},
{"id":650,"first_name":"Kriste","last_name":"Treweke","email":"ktrewekei1@google.ru"},
{"id":651,"first_name":"Gabriell","last_name":"Salter","email":"gsalteri2@reverbnation.com"},
{"id":652,"first_name":"Gertrud","last_name":"Ethington","email":"gethingtoni3@bandcamp.com"},
{"id":653,"first_name":"Esmeralda","last_name":"Arstall","email":"earstalli4@netvibes.com"},
{"id":654,"first_name":"Cris","last_name":"Brussell","email":"cbrusselli5@eepurl.com"},
{"id":655,"first_name":"Tabina","last_name":"Thickin","email":"tthickini6@un.org"},
{"id":656,"first_name":"Vanessa","last_name":"Keyzor","email":"vkeyzori7@google.com.au"},
{"id":657,"first_name":"Halette","last_name":"Moulton","email":"hmoultoni8@thetimes.co.uk"},
{"id":658,"first_name":"Bernardine","last_name":"Pakenham","email":"bpakenhami9@google.co.jp"},
{"id":659,"first_name":"Nelle","last_name":"Spinke","email":"nspinkeia@icio.us"},
{"id":660,"first_name":"Rene","last_name":"McNamara","email":"rmcnamaraib@jimdo.com"},
{"id":661,"first_name":"Peyton","last_name":"Cicchelli","email":"pcicchelliic@addtoany.com"},
{"id":662,"first_name":"Gonzalo","last_name":"Gimeno","email":"ggimenoid@elpais.com"},
{"id":663,"first_name":"Livy","last_name":"Oxby","email":"loxbyie@ezinearticles.com"},
{"id":664,"first_name":"Warde","last_name":"Tayt","email":"wtaytif@ucla.edu"},
{"id":665,"first_name":"Stanfield","last_name":"McCullen","email":"smccullenig@alibaba.com"},
{"id":666,"first_name":"Tabbitha","last_name":"Langham","email":"tlanghamih@dailymotion.com"},
{"id":667,"first_name":"Kinnie","last_name":"Windows","email":"kwindowsii@dailymotion.com"},
{"id":668,"first_name":"Dal","last_name":"Facher","email":"dfacherij@earthlink.net"},
{"id":669,"first_name":"Savina","last_name":"Muckle","email":"smuckleik@reddit.com"},
{"id":670,"first_name":"Jasen","last_name":"Ferne","email":"jferneil@lulu.com"},
{"id":671,"first_name":"Harvey","last_name":"Claypool","email":"hclaypoolim@ihg.com"},
{"id":672,"first_name":"Edy","last_name":"Ten Broek","email":"etenbroekin@thetimes.co.uk"},
{"id":673,"first_name":"Trisha","last_name":"Souza","email":"tsouzaio@washingtonpost.com"},
{"id":674,"first_name":"Judye","last_name":"Gebuhr","email":"jgebuhrip@github.com"},
{"id":675,"first_name":"Arnuad","last_name":"Bullin","email":"abulliniq@netlog.com"},
{"id":676,"first_name":"Terri-jo","last_name":"Perassi","email":"tperassiir@freewebs.com"},
{"id":677,"first_name":"Washington","last_name":"Chevalier","email":"wchevalieris@unblog.fr"},
{"id":678,"first_name":"Lonee","last_name":"Diver","email":"ldiverit@usgs.gov"},
{"id":679,"first_name":"Corilla","last_name":"Cassimer","email":"ccassimeriu@51.la"},
{"id":680,"first_name":"Thane","last_name":"Gillie","email":"tgillieiv@unblog.fr"},
{"id":681,"first_name":"Zebedee","last_name":"Andreichik","email":"zandreichikiw@imageshack.us"},
{"id":682,"first_name":"Glyn","last_name":"Reinhart","email":"greinhartix@fastcompany.com"},
{"id":683,"first_name":"Adelbert","last_name":"Barbera","email":"abarberaiy@spiegel.de"},
{"id":684,"first_name":"Beckie","last_name":"Croose","email":"bcrooseiz@purevolume.com"},
{"id":685,"first_name":"Garner","last_name":"Armistead","email":"garmisteadj0@lycos.com"},
{"id":686,"first_name":"Beau","last_name":"Sandys","email":"bsandysj1@forbes.com"},
{"id":687,"first_name":"Rozanne","last_name":"Surmon","email":"rsurmonj2@discovery.com"},
{"id":688,"first_name":"Thain","last_name":"Broadbere","email":"tbroadberej3@diigo.com"},
{"id":689,"first_name":"Linn","last_name":"Stringer","email":"lstringerj4@furl.net"},
{"id":690,"first_name":"Rodie","last_name":"Getley","email":"rgetleyj5@joomla.org"},
{"id":691,"first_name":"Opal","last_name":"Eadon","email":"oeadonj6@nih.gov"},
{"id":692,"first_name":"Lloyd","last_name":"Lunck","email":"llunckj7@plala.or.jp"},
{"id":693,"first_name":"Zorah","last_name":"Nizard","email":"znizardj8@constantcontact.com"},
{"id":694,"first_name":"Pam","last_name":"McBrearty","email":"pmcbreartyj9@bandcamp.com"},
{"id":695,"first_name":"Danica","last_name":"Gowry","email":"dgowryja@samsung.com"},
{"id":696,"first_name":"Chelsae","last_name":"Guerin","email":"cguerinjb@phpbb.com"},
{"id":697,"first_name":"Gerri","last_name":"Acors","email":"gacorsjc@fda.gov"},
{"id":698,"first_name":"Wyatan","last_name":"Tire","email":"wtirejd@4shared.com"},
{"id":699,"first_name":"Elias","last_name":"Beardsall","email":"ebeardsallje@mit.edu"},
{"id":700,"first_name":"Nata","last_name":"Clabburn","email":"nclabburnjf@tinyurl.com"},
{"id":701,"first_name":"Coraline","last_name":"Mayell","email":"cmayelljg@netvibes.com"},
{"id":702,"first_name":"Tyler","last_name":"Duran","email":"tduranjh@gravatar.com"},
{"id":703,"first_name":"Caren","last_name":"Massei","email":"cmasseiji@biblegateway.com"},
{"id":704,"first_name":"Waneta","last_name":"Gagan","email":"wgaganjj@istockphoto.com"},
{"id":705,"first_name":"Artemus","last_name":"Gare","email":"agarejk@ameblo.jp"},
{"id":706,"first_name":"Odo","last_name":"Fletham","email":"oflethamjl@webnode.com"},
{"id":707,"first_name":"Kara","last_name":"MacCrossan","email":"kmaccrossanjm@cdbaby.com"},
{"id":708,"first_name":"Cristy","last_name":"Berrygun","email":"cberrygunjn@gov.uk"},
{"id":709,"first_name":"Matelda","last_name":"Jankowski","email":"mjankowskijo@people.com.cn"},
{"id":710,"first_name":"Elga","last_name":"Sanchez","email":"esanchezjp@123-reg.co.uk"},
{"id":711,"first_name":"Dilly","last_name":"Marian","email":"dmarianjq@hugedomains.com"},
{"id":712,"first_name":"Hubert","last_name":"Finnimore","email":"hfinnimorejr@umn.edu"},
{"id":713,"first_name":"Bertie","last_name":"Woodhall","email":"bwoodhalljs@instagram.com"},
{"id":714,"first_name":"Cathryn","last_name":"Mogenot","email":"cmogenotjt@techcrunch.com"},
{"id":715,"first_name":"Elvin","last_name":"MacIntyre","email":"emacintyreju@goo.gl"},
{"id":716,"first_name":"Marlo","last_name":"Bassom","email":"mbassomjv@addtoany.com"},
{"id":717,"first_name":"Fairlie","last_name":"Byatt","email":"fbyattjw@1und1.de"},
{"id":718,"first_name":"Bernie","last_name":"Ainslee","email":"bainsleejx@go.com"},
{"id":719,"first_name":"Ker","last_name":"Daw","email":"kdawjy@google.com.hk"},
{"id":720,"first_name":"Bill","last_name":"Parton","email":"bpartonjz@acquirethisname.com"},
{"id":721,"first_name":"Abram","last_name":"Drakeley","email":"adrakeleyk0@wsj.com"},
{"id":722,"first_name":"Carly","last_name":"Elcox","email":"celcoxk1@zdnet.com"},
{"id":723,"first_name":"Gustaf","last_name":"Danson","email":"gdansonk2@discovery.com"},
{"id":724,"first_name":"Ardyce","last_name":"Delaprelle","email":"adelaprellek3@sphinn.com"},
{"id":725,"first_name":"Tandy","last_name":"Brahms","email":"tbrahmsk4@ning.com"},
{"id":726,"first_name":"Wit","last_name":"Estcot","email":"westcotk5@globo.com"},
{"id":727,"first_name":"Coriss","last_name":"Farquhar","email":"cfarquhark6@thetimes.co.uk"},
{"id":728,"first_name":"Theresina","last_name":"Hayford","email":"thayfordk7@earthlink.net"},
{"id":729,"first_name":"Rollin","last_name":"Porcher","email":"rporcherk8@yolasite.com"},
{"id":730,"first_name":"Geneva","last_name":"Gratrex","email":"ggratrexk9@geocities.com"},
{"id":731,"first_name":"Shaughn","last_name":"Brute","email":"sbruteka@techcrunch.com"},
{"id":732,"first_name":"Wendeline","last_name":"Edwick","email":"wedwickkb@spotify.com"},
{"id":733,"first_name":"Katya","last_name":"Killcross","email":"kkillcrosskc@nationalgeographic.com"},
{"id":734,"first_name":"Louella","last_name":"Gilardoni","email":"lgilardonikd@sbwire.com"},
{"id":735,"first_name":"Chas","last_name":"Cowton","email":"ccowtonke@myspace.com"},
{"id":736,"first_name":"Lizzie","last_name":"Goublier","email":"lgoublierkf@theatlantic.com"},
{"id":737,"first_name":"Gabbie","last_name":"Bodle","email":"gbodlekg@indiatimes.com"},
{"id":738,"first_name":"Reinwald","last_name":"Frankis","email":"rfrankiskh@php.net"},
{"id":739,"first_name":"Isabeau","last_name":"Wensley","email":"iwensleyki@stanford.edu"},
{"id":740,"first_name":"Carlotta","last_name":"Atwill","email":"catwillkj@usgs.gov"},
{"id":741,"first_name":"Ramsay","last_name":"Jelkes","email":"rjelkeskk@ftc.gov"},
{"id":742,"first_name":"Lucretia","last_name":"Jatczak","email":"ljatczakkl@free.fr"},
{"id":743,"first_name":"Jayson","last_name":"Haskew","email":"jhaskewkm@networkadvertising.org"},
{"id":744,"first_name":"Zolly","last_name":"Matterface","email":"zmatterfacekn@jiathis.com"},
{"id":745,"first_name":"Denver","last_name":"McQuillan","email":"dmcquillanko@shinystat.com"},
{"id":746,"first_name":"Matthaeus","last_name":"Binton","email":"mbintonkp@ow.ly"},
{"id":747,"first_name":"Zelda","last_name":"Gracey","email":"zgraceykq@hubpages.com"},
{"id":748,"first_name":"Raff","last_name":"Loddon","email":"rloddonkr@samsung.com"},
{"id":749,"first_name":"Lin","last_name":"Plum","email":"lplumks@usa.gov"},
{"id":750,"first_name":"Gloriane","last_name":"Arlidge","email":"garlidgekt@cafepress.com"},
{"id":751,"first_name":"Merola","last_name":"Obell","email":"mobellku@eventbrite.com"},
{"id":752,"first_name":"Cleon","last_name":"Kerswell","email":"ckerswellkv@icio.us"},
{"id":753,"first_name":"Laure","last_name":"Willett","email":"lwillettkw@livejournal.com"},
{"id":754,"first_name":"Leora","last_name":"Yukhin","email":"lyukhinkx@unc.edu"},
{"id":755,"first_name":"Jennette","last_name":"Loder","email":"jloderky@usa.gov"},
{"id":756,"first_name":"Dana","last_name":"Helstrip","email":"dhelstripkz@people.com.cn"},
{"id":757,"first_name":"Erastus","last_name":"Twizell","email":"etwizelll0@jimdo.com"},
{"id":758,"first_name":"Ware","last_name":"Toretta","email":"wtorettal1@fema.gov"},
{"id":759,"first_name":"Lisle","last_name":"Lagadu","email":"llagadul2@yahoo.co.jp"},
{"id":760,"first_name":"Brinn","last_name":"Bisseker","email":"bbissekerl3@hp.com"},
{"id":761,"first_name":"Ravi","last_name":"Iamittii","email":"riamittiil4@livejournal.com"},
{"id":762,"first_name":"Sander","last_name":"Bonanno","email":"sbonannol5@flickr.com"},
{"id":763,"first_name":"Bernardine","last_name":"Tinwell","email":"btinwelll6@weibo.com"},
{"id":764,"first_name":"Gilligan","last_name":"Frantsev","email":"gfrantsevl7@uiuc.edu"},
{"id":765,"first_name":"Selinda","last_name":"Grumley","email":"sgrumleyl8@irs.gov"},
{"id":766,"first_name":"Aigneis","last_name":"Streatfield","email":"astreatfieldl9@oakley.com"},
{"id":767,"first_name":"Ronny","last_name":"McKibben","email":"rmckibbenla@nymag.com"},
{"id":768,"first_name":"Winna","last_name":"Godbald","email":"wgodbaldlb@surveymonkey.com"},
{"id":769,"first_name":"Malchy","last_name":"Shillingford","email":"mshillingfordlc@indiatimes.com"},
{"id":770,"first_name":"Oralie","last_name":"Strelitzer","email":"ostrelitzerld@over-blog.com"},
{"id":771,"first_name":"Yorker","last_name":"Sager","email":"ysagerle@prnewswire.com"},
{"id":772,"first_name":"Jarrett","last_name":"Garrick","email":"jgarricklf@jigsy.com"},
{"id":773,"first_name":"Mattie","last_name":"Chicken","email":"mchickenlg@tiny.cc"},
{"id":774,"first_name":"Milicent","last_name":"Denizet","email":"mdenizetlh@yolasite.com"},
{"id":775,"first_name":"Tucky","last_name":"Hasser","email":"thasserli@wikia.com"},
{"id":776,"first_name":"Jemimah","last_name":"Bly","email":"jblylj@apple.com"},
{"id":777,"first_name":"Innis","last_name":"Hubber","email":"ihubberlk@tumblr.com"},
{"id":778,"first_name":"Rickie","last_name":"Kimberley","email":"rkimberleyll@utexas.edu"},
{"id":779,"first_name":"Greer","last_name":"Alwell","email":"galwelllm@ehow.com"},
{"id":780,"first_name":"Michele","last_name":"Durrans","email":"mdurransln@bluehost.com"},
{"id":781,"first_name":"Sammie","last_name":"Cropp","email":"scropplo@sina.com.cn"},
{"id":782,"first_name":"Golda","last_name":"Commings","email":"gcommingslp@nature.com"},
{"id":783,"first_name":"Malvina","last_name":"Sutherley","email":"msutherleylq@imgur.com"},
{"id":784,"first_name":"Sonny","last_name":"Sowman","email":"ssowmanlr@discovery.com"},
{"id":785,"first_name":"Herminia","last_name":"Goold","email":"hgooldls@fc2.com"},
{"id":786,"first_name":"Winna","last_name":"Scriven","email":"wscrivenlt@clickbank.net"},
{"id":787,"first_name":"Kat","last_name":"Stoade","email":"kstoadelu@nih.gov"},
{"id":788,"first_name":"Isidora","last_name":"Coviello","email":"icoviellolv@ucsd.edu"},
{"id":789,"first_name":"Abbe","last_name":"Spehr","email":"aspehrlw@photobucket.com"},
{"id":790,"first_name":"Laverne","last_name":"Chastanet","email":"lchastanetlx@samsung.com"},
{"id":791,"first_name":"Alessandro","last_name":"Melody","email":"amelodyly@e-recht24.de"},
{"id":792,"first_name":"Marne","last_name":"Amies","email":"mamieslz@miibeian.gov.cn"},
{"id":793,"first_name":"Ronna","last_name":"Hazeldean","email":"rhazeldeanm0@a8.net"},
{"id":794,"first_name":"Jessy","last_name":"Ribey","email":"jribeym1@mozilla.com"},
{"id":795,"first_name":"Halette","last_name":"Biddy","email":"hbiddym2@usnews.com"},
{"id":796,"first_name":"Alley","last_name":"Durrans","email":"adurransm3@privacy.gov.au"},
{"id":797,"first_name":"Monica","last_name":"Dytham","email":"mdythamm4@dagondesign.com"},
{"id":798,"first_name":"Philippe","last_name":"Teague","email":"pteaguem5@sohu.com"},
{"id":799,"first_name":"Lenette","last_name":"Essex","email":"lessexm6@guardian.co.uk"},
{"id":800,"first_name":"Malanie","last_name":"Le Friec","email":"mlefriecm7@themeforest.net"},
{"id":801,"first_name":"Eulalie","last_name":"Croster","email":"ecrosterm8@dion.ne.jp"},
{"id":802,"first_name":"Darcy","last_name":"Tuffley","email":"dtuffleym9@squidoo.com"},
{"id":803,"first_name":"Beale","last_name":"Saipy","email":"bsaipyma@smugmug.com"},
{"id":804,"first_name":"Webb","last_name":"Tebald","email":"wtebaldmb@nih.gov"},
{"id":805,"first_name":"Sonia","last_name":"Cloney","email":"scloneymc@umn.edu"},
{"id":806,"first_name":"Charmion","last_name":"Gayden","email":"cgaydenmd@soundcloud.com"},
{"id":807,"first_name":"Delores","last_name":"Gibbens","email":"dgibbensme@spotify.com"},
{"id":808,"first_name":"Erda","last_name":"Carlin","email":"ecarlinmf@umn.edu"},
{"id":809,"first_name":"Catharina","last_name":"Godly","email":"cgodlymg@wikispaces.com"},
{"id":810,"first_name":"Wernher","last_name":"Yeatman","email":"wyeatmanmh@who.int"},
{"id":811,"first_name":"Shirlene","last_name":"Buckwell","email":"sbuckwellmi@php.net"},
{"id":812,"first_name":"Lenci","last_name":"Wilcott","email":"lwilcottmj@nature.com"},
{"id":813,"first_name":"Antone","last_name":"Ebbotts","email":"aebbottsmk@sciencedaily.com"},
{"id":814,"first_name":"Tabor","last_name":"Farden","email":"tfardenml@desdev.cn"},
{"id":815,"first_name":"Kari","last_name":"Cashin","email":"kcashinmm@wsj.com"},
{"id":816,"first_name":"Rabi","last_name":"Hearnes","email":"rhearnesmn@gov.uk"},
{"id":817,"first_name":"Edgar","last_name":"Drain","email":"edrainmo@hao123.com"},
{"id":818,"first_name":"Robinet","last_name":"Reese","email":"rreesemp@soundcloud.com"},
{"id":819,"first_name":"Dolly","last_name":"Quakley","email":"dquakleymq@w3.org"},
{"id":820,"first_name":"Mayne","last_name":"MacIan","email":"mmacianmr@umn.edu"},
{"id":821,"first_name":"Ellyn","last_name":"Mackinder","email":"emackinderms@blogger.com"},
{"id":822,"first_name":"Donella","last_name":"Tolfrey","email":"dtolfreymt@dagondesign.com"},
{"id":823,"first_name":"Galvin","last_name":"Sephton","email":"gsephtonmu@cnbc.com"},
{"id":824,"first_name":"Rivkah","last_name":"Randal","email":"rrandalmv@so-net.ne.jp"},
{"id":825,"first_name":"Nikkie","last_name":"Christie","email":"nchristiemw@telegraph.co.uk"},
{"id":826,"first_name":"Griffy","last_name":"McCaughey","email":"gmccaugheymx@loc.gov"},
{"id":827,"first_name":"Theresina","last_name":"Sabbatier","email":"tsabbatiermy@webmd.com"},
{"id":828,"first_name":"Kean","last_name":"Leap","email":"kleapmz@scribd.com"},
{"id":829,"first_name":"Ailina","last_name":"Robbert","email":"arobbertn0@nymag.com"},
{"id":830,"first_name":"Otto","last_name":"Melesk","email":"omeleskn1@yellowpages.com"},
{"id":831,"first_name":"Bartholomeus","last_name":"Bilbee","email":"bbilbeen2@bravesites.com"},
{"id":832,"first_name":"Richie","last_name":"Tree","email":"rtreen3@t.co"},
{"id":833,"first_name":"Rebeca","last_name":"Stockney","email":"rstockneyn4@netlog.com"},
{"id":834,"first_name":"Katinka","last_name":"Wardington","email":"kwardingtonn5@mashable.com"},
{"id":835,"first_name":"Georgy","last_name":"Blower","email":"gblowern6@skype.com"},
{"id":836,"first_name":"Finlay","last_name":"Elwood","email":"felwoodn7@seesaa.net"},
{"id":837,"first_name":"Adelaide","last_name":"Beringer","email":"aberingern8@facebook.com"},
{"id":838,"first_name":"Jacquenetta","last_name":"Sharper","email":"jsharpern9@de.vu"},
{"id":839,"first_name":"Angeli","last_name":"Lyons","email":"alyonsna@wiley.com"},
{"id":840,"first_name":"Trent","last_name":"Bottelstone","email":"tbottelstonenb@google.com.br"},
{"id":841,"first_name":"Jemmy","last_name":"Frankling","email":"jfranklingnc@examiner.com"},
{"id":842,"first_name":"Natty","last_name":"Bevir","email":"nbevirnd@google.de"},
{"id":843,"first_name":"Kinna","last_name":"Carrel","email":"kcarrelne@cbc.ca"},
{"id":844,"first_name":"Jeff","last_name":"MacHostie","email":"jmachostienf@wisc.edu"},
{"id":845,"first_name":"Cicely","last_name":"Cabrera","email":"ccabrerang@sciencedaily.com"},
{"id":846,"first_name":"Odette","last_name":"Saltwell","email":"osaltwellnh@google.co.jp"},
{"id":847,"first_name":"Albertina","last_name":"Blunsum","email":"ablunsumni@mlb.com"},
{"id":848,"first_name":"Sebastiano","last_name":"McGrayle","email":"smcgraylenj@mysql.com"},
{"id":849,"first_name":"Ives","last_name":"Geere","email":"igeerenk@ft.com"},
{"id":850,"first_name":"Kerry","last_name":"Wilkennson","email":"kwilkennsonnl@soundcloud.com"},
{"id":851,"first_name":"Margaretta","last_name":"Jedras","email":"mjedrasnm@imdb.com"},
{"id":852,"first_name":"Maura","last_name":"Whitington","email":"mwhitingtonnn@webmd.com"},
{"id":853,"first_name":"Seward","last_name":"Simkiss","email":"ssimkissno@technorati.com"},
{"id":854,"first_name":"Roseline","last_name":"Goudman","email":"rgoudmannp@qq.com"},
{"id":855,"first_name":"Corrine","last_name":"Beamand","email":"cbeamandnq@barnesandnoble.com"},
{"id":856,"first_name":"Myrilla","last_name":"Christal","email":"mchristalnr@ucoz.com"},
{"id":857,"first_name":"Olga","last_name":"Kettles","email":"okettlesns@blogspot.com"},
{"id":858,"first_name":"Walker","last_name":"Isac","email":"wisacnt@zdnet.com"},
{"id":859,"first_name":"Jermayne","last_name":"MacGowan","email":"jmacgowannu@pen.io"},
{"id":860,"first_name":"Gianna","last_name":"Ritch","email":"gritchnv@tripod.com"},
{"id":861,"first_name":"Felita","last_name":"Dyde","email":"fdydenw@t.co"},
{"id":862,"first_name":"Rudd","last_name":"De Roberto","email":"rderobertonx@miitbeian.gov.cn"},
{"id":863,"first_name":"Sharai","last_name":"Jeger","email":"sjegerny@addthis.com"},
{"id":864,"first_name":"Jeffy","last_name":"Cayzer","email":"jcayzernz@wikipedia.org"},
{"id":865,"first_name":"Christoph","last_name":"Perry","email":"cperryo0@paginegialle.it"},
{"id":866,"first_name":"Tan","last_name":"Rosenfeld","email":"trosenfeldo1@wiley.com"},
{"id":867,"first_name":"Brittney","last_name":"McIlharga","email":"bmcilhargao2@cargocollective.com"},
{"id":868,"first_name":"Fay","last_name":"Harcase","email":"fharcaseo3@desdev.cn"},
{"id":869,"first_name":"Stanwood","last_name":"Toward","email":"stowardo4@nyu.edu"},
{"id":870,"first_name":"Hermina","last_name":"Mardlin","email":"hmardlino5@earthlink.net"},
{"id":871,"first_name":"Lemmie","last_name":"Coode","email":"lcoodeo6@nifty.com"},
{"id":872,"first_name":"Cyndy","last_name":"Nazer","email":"cnazero7@ca.gov"},
{"id":873,"first_name":"Bellanca","last_name":"Tiery","email":"btieryo8@ezinearticles.com"},
{"id":874,"first_name":"Carr","last_name":"Sopper","email":"csoppero9@java.com"},
{"id":875,"first_name":"Geoffry","last_name":"Kynoch","email":"gkynochoa@hc360.com"},
{"id":876,"first_name":"Verena","last_name":"Andrassy","email":"vandrassyob@npr.org"},
{"id":877,"first_name":"Mart","last_name":"Soot","email":"msootoc@moonfruit.com"},
{"id":878,"first_name":"Erick","last_name":"Tressler","email":"etresslerod@pinterest.com"},
{"id":879,"first_name":"Ryann","last_name":"Hartfleet","email":"rhartfleetoe@uiuc.edu"},
{"id":880,"first_name":"Erhart","last_name":"Nano","email":"enanoof@amazon.co.jp"},
{"id":881,"first_name":"Nicky","last_name":"Hemmingway","email":"nhemmingwayog@freewebs.com"},
{"id":882,"first_name":"Deeyn","last_name":"Tregenza","email":"dtregenzaoh@foxnews.com"},
{"id":883,"first_name":"Heindrick","last_name":"Ewers","email":"hewersoi@elegantthemes.com"},
{"id":884,"first_name":"Tiler","last_name":"Domini","email":"tdominioj@i2i.jp"},
{"id":885,"first_name":"Collete","last_name":"Worvell","email":"cworvellok@cargocollective.com"},
{"id":886,"first_name":"Viole","last_name":"Moubray","email":"vmoubrayol@abc.net.au"},
{"id":887,"first_name":"Larina","last_name":"Byforth","email":"lbyforthom@stumbleupon.com"},
{"id":888,"first_name":"Lin","last_name":"Aust","email":"lauston@clickbank.net"},
{"id":889,"first_name":"Angelia","last_name":"Skarman","email":"askarmanoo@cafepress.com"},
{"id":890,"first_name":"Midge","last_name":"Ewells","email":"mewellsop@bandcamp.com"},
{"id":891,"first_name":"Bertie","last_name":"Rounsefull","email":"brounsefulloq@e-recht24.de"},
{"id":892,"first_name":"Celina","last_name":"Conradsen","email":"cconradsenor@ovh.net"},
{"id":893,"first_name":"Cherice","last_name":"Bartholomew","email":"cbartholomewos@yelp.com"},
{"id":894,"first_name":"Diahann","last_name":"Dow","email":"ddowot@apache.org"},
{"id":895,"first_name":"Hodge","last_name":"Alpes","email":"halpesou@ameblo.jp"},
{"id":896,"first_name":"Crichton","last_name":"Foro","email":"cforoov@instagram.com"},
{"id":897,"first_name":"Ozzie","last_name":"Bezley","email":"obezleyow@mac.com"},
{"id":898,"first_name":"Monro","last_name":"Jeanenet","email":"mjeanenetox@jigsy.com"},
{"id":899,"first_name":"Abigail","last_name":"Order","email":"aorderoy@npr.org"},
{"id":900,"first_name":"Cecil","last_name":"Jolley","email":"cjolleyoz@loc.gov"},
{"id":901,"first_name":"Hermine","last_name":"O'Regan","email":"horeganp0@ihg.com"},
{"id":902,"first_name":"Esme","last_name":"Slate","email":"eslatep1@vkontakte.ru"},
{"id":903,"first_name":"Aurie","last_name":"Guillon","email":"aguillonp2@eventbrite.com"},
{"id":904,"first_name":"Maggi","last_name":"Norrey","email":"mnorreyp3@shutterfly.com"},
{"id":905,"first_name":"Dode","last_name":"Crispe","email":"dcrispep4@zdnet.com"},
{"id":906,"first_name":"Susette","last_name":"Veltmann","email":"sveltmannp5@oakley.com"},
{"id":907,"first_name":"Lily","last_name":"Pervew","email":"lpervewp6@meetup.com"},
{"id":908,"first_name":"Erhart","last_name":"Pettus","email":"epettusp7@macromedia.com"},
{"id":909,"first_name":"Bernette","last_name":"Dall","email":"bdallp8@hhs.gov"},
{"id":910,"first_name":"Wald","last_name":"Flux","email":"wfluxp9@livejournal.com"},
{"id":911,"first_name":"Margalit","last_name":"Grossman","email":"mgrossmanpa@loc.gov"},
{"id":912,"first_name":"Burch","last_name":"Menel","email":"bmenelpb@comcast.net"},
{"id":913,"first_name":"Stephine","last_name":"Hughf","email":"shughfpc@mit.edu"},
{"id":914,"first_name":"Phillis","last_name":"Morrow","email":"pmorrowpd@multiply.com"},
{"id":915,"first_name":"Krystal","last_name":"Welford","email":"kwelfordpe@bigcartel.com"},
{"id":916,"first_name":"Ibrahim","last_name":"Maly","email":"imalypf@tiny.cc"},
{"id":917,"first_name":"Rozina","last_name":"Yerbury","email":"ryerburypg@elegantthemes.com"},
{"id":918,"first_name":"Donaugh","last_name":"Harrad","email":"dharradph@narod.ru"},
{"id":919,"first_name":"Monah","last_name":"Mingardo","email":"mmingardopi@exblog.jp"},
{"id":920,"first_name":"Lanie","last_name":"Tinston","email":"ltinstonpj@jalbum.net"},
{"id":921,"first_name":"Damita","last_name":"Aubery","email":"dauberypk@mashable.com"},
{"id":922,"first_name":"Uriel","last_name":"Schreiner","email":"uschreinerpl@cyberchimps.com"},
{"id":923,"first_name":"Rosemaria","last_name":"Andree","email":"randreepm@globo.com"},
{"id":924,"first_name":"Josy","last_name":"Schimek","email":"jschimekpn@ted.com"},
{"id":925,"first_name":"Natty","last_name":"Beebis","email":"nbeebispo@clickbank.net"},
{"id":926,"first_name":"Zebedee","last_name":"Martonfi","email":"zmartonfipp@wix.com"},
{"id":927,"first_name":"Bird","last_name":"Burrill","email":"bburrillpq@tumblr.com"},
{"id":928,"first_name":"Luis","last_name":"Dallewater","email":"ldallewaterpr@booking.com"},
{"id":929,"first_name":"Lew","last_name":"Leaming","email":"lleamingps@amazon.de"},
{"id":930,"first_name":"Rolando","last_name":"Voelker","email":"rvoelkerpt@google.com.au"},
{"id":931,"first_name":"Chrystel","last_name":"Hadye","email":"chadyepu@ftc.gov"},
{"id":932,"first_name":"Esme","last_name":"Hannen","email":"ehannenpv@cornell.edu"},
{"id":933,"first_name":"Clement","last_name":"Cromie","email":"ccromiepw@surveymonkey.com"},
{"id":934,"first_name":"Lira","last_name":"Seneschal","email":"lseneschalpx@home.pl"},
{"id":935,"first_name":"Amitie","last_name":"Vogl","email":"avoglpy@aol.com"},
{"id":936,"first_name":"Lucia","last_name":"O'Lunny","email":"lolunnypz@archive.org"},
{"id":937,"first_name":"Julia","last_name":"McManamen","email":"jmcmanamenq0@symantec.com"},
{"id":938,"first_name":"Lorens","last_name":"Quail","email":"lquailq1@skyrock.com"},
{"id":939,"first_name":"Devy","last_name":"Josland","email":"djoslandq2@ibm.com"},
{"id":940,"first_name":"Judd","last_name":"Valenta","email":"jvalentaq3@foxnews.com"},
{"id":941,"first_name":"Arnie","last_name":"Villa","email":"avillaq4@drupal.org"},
{"id":942,"first_name":"Corney","last_name":"Harsant","email":"charsantq5@nsw.gov.au"},
{"id":943,"first_name":"Hersch","last_name":"Hamlet","email":"hhamletq6@about.com"},
{"id":944,"first_name":"Daisie","last_name":"Janaway","email":"djanawayq7@prweb.com"},
{"id":945,"first_name":"Sheba","last_name":"Creboe","email":"screboeq8@nhs.uk"},
{"id":946,"first_name":"Hardy","last_name":"Kippax","email":"hkippaxq9@techcrunch.com"},
{"id":947,"first_name":"Linnie","last_name":"Howley","email":"lhowleyqa@unc.edu"},
{"id":948,"first_name":"Sofia","last_name":"Nuton","email":"snutonqb@webeden.co.uk"},
{"id":949,"first_name":"Kristoffer","last_name":"Wrist","email":"kwristqc@fotki.com"},
{"id":950,"first_name":"Natalee","last_name":"Will","email":"nwillqd@networkadvertising.org"},
{"id":951,"first_name":"Candra","last_name":"Bullivant","email":"cbullivantqe@intel.com"},
{"id":952,"first_name":"Miquela","last_name":"Solomonides","email":"msolomonidesqf@youtube.com"},
{"id":953,"first_name":"Amy","last_name":"Nutten","email":"anuttenqg@dmoz.org"},
{"id":954,"first_name":"Viviyan","last_name":"Cotter","email":"vcotterqh@squarespace.com"},
{"id":955,"first_name":"Berny","last_name":"Springett","email":"bspringettqi@upenn.edu"},
{"id":956,"first_name":"Berni","last_name":"Tomich","email":"btomichqj@storify.com"},
{"id":957,"first_name":"Nanete","last_name":"Gonneau","email":"ngonneauqk@opensource.org"},
{"id":958,"first_name":"Harwell","last_name":"Heinsius","email":"hheinsiusql@networkadvertising.org"},
{"id":959,"first_name":"Rosemaria","last_name":"Butting","email":"rbuttingqm@live.com"},
{"id":960,"first_name":"Guthrie","last_name":"Dunbavin","email":"gdunbavinqn@cmu.edu"},
{"id":961,"first_name":"Timmy","last_name":"Stanning","email":"tstanningqo@cornell.edu"},
{"id":962,"first_name":"Rennie","last_name":"Ligoe","email":"rligoeqp@tiny.cc"},
{"id":963,"first_name":"Thorvald","last_name":"Klimov","email":"tklimovqq@ca.gov"},
{"id":964,"first_name":"Gamaliel","last_name":"Coupland","email":"gcouplandqr@hexun.com"},
{"id":965,"first_name":"Merrile","last_name":"Flaws","email":"mflawsqs@usa.gov"},
{"id":966,"first_name":"Theresina","last_name":"Bigglestone","email":"tbigglestoneqt@eepurl.com"},
{"id":967,"first_name":"Merrick","last_name":"Verdie","email":"mverdiequ@twitter.com"},
{"id":968,"first_name":"Johny","last_name":"Lyburn","email":"jlyburnqv@netvibes.com"},
{"id":969,"first_name":"Blondelle","last_name":"Gallgher","email":"bgallgherqw@chicagotribune.com"},
{"id":970,"first_name":"Dolli","last_name":"Grimsdyke","email":"dgrimsdykeqx@dagondesign.com"},
{"id":971,"first_name":"Patricio","last_name":"Mordey","email":"pmordeyqy@php.net"},
{"id":972,"first_name":"Gwenny","last_name":"Leftley","email":"gleftleyqz@typepad.com"},
{"id":973,"first_name":"Rebecca","last_name":"Revie","email":"rrevier0@typepad.com"},
{"id":974,"first_name":"Dasha","last_name":"Phateplace","email":"dphateplacer1@amazon.co.uk"},
{"id":975,"first_name":"Desi","last_name":"Fresson","email":"dfressonr2@tumblr.com"},
{"id":976,"first_name":"Blaine","last_name":"Lyons","email":"blyonsr3@cbslocal.com"},
{"id":977,"first_name":"Zacharia","last_name":"Skerm","email":"zskermr4@google.de"},
{"id":978,"first_name":"Mame","last_name":"Joist","email":"mjoistr5@dailymotion.com"},
{"id":979,"first_name":"Emogene","last_name":"Arrigucci","email":"earriguccir6@booking.com"},
{"id":980,"first_name":"Rollo","last_name":"Scadden","email":"rscaddenr7@histats.com"},
{"id":981,"first_name":"Erhard","last_name":"Bartens","email":"ebartensr8@jalbum.net"},
{"id":982,"first_name":"Cherri","last_name":"MacRory","email":"cmacroryr9@behance.net"},
{"id":983,"first_name":"Isidro","last_name":"Curdell","email":"icurdellra@dmoz.org"},
{"id":984,"first_name":"Osmund","last_name":"Wombwell","email":"owombwellrb@github.io"},
{"id":985,"first_name":"Kordula","last_name":"O'Connel","email":"koconnelrc@ovh.net"},
{"id":986,"first_name":"Hastings","last_name":"Aujean","email":"haujeanrd@springer.com"},
{"id":987,"first_name":"Rivkah","last_name":"Penticost","email":"rpenticostre@reddit.com"},
{"id":988,"first_name":"Luther","last_name":"Devlin","email":"ldevlinrf@163.com"},
{"id":989,"first_name":"Suzann","last_name":"Quennell","email":"squennellrg@joomla.org"},
{"id":990,"first_name":"Johny","last_name":"Stopford","email":"jstopfordrh@google.com"},
{"id":991,"first_name":"Tate","last_name":"Smithson","email":"tsmithsonri@elegantthemes.com"},
{"id":992,"first_name":"Hilly","last_name":"Olenchikov","email":"holenchikovrj@mlb.com"},
{"id":993,"first_name":"Jobie","last_name":"Yakushkin","email":"jyakushkinrk@jimdo.com"},
{"id":994,"first_name":"Jakie","last_name":"Emmet","email":"jemmetrl@si.edu"},
{"id":995,"first_name":"Tersina","last_name":"Brandino","email":"tbrandinorm@archive.org"},
{"id":996,"first_name":"Fiona","last_name":"Mallison","email":"fmallisonrn@sakura.ne.jp"},
{"id":997,"first_name":"Leelah","last_name":"Toppes","email":"ltoppesro@smugmug.com"},
{"id":998,"first_name":"Katti","last_name":"Stonuary","email":"kstonuaryrp@joomla.org"},
{"id":999,"first_name":"Ty","last_name":"Inold","email":"tinoldrq@g.co"},
{"id":1000,"first_name":"Sileas","last_name":"Phare","email":"spharerr@webs.com"}]